{
  "task_meta": {},
  "annotations": [
    {
      "id": "2b411152-1cc7-4665-b5d8-e78de69292da",
      "new": true,
      "parent_id": null,
      "created_by": "sarah_peterson",
      "created_at": "2020-08-03T21:40:01Z",
      "deprecated": false,
      "spatial_type": "bbox3",
      "spatial_payload": [
        [
          147.28570992606026,
          201.0,
          55.0
        ],
        [
          375.14320992606025,
          328.1432142857143,
          99.0
        ]
      ],
      "classification_payloads": [
        {
          "class_id": 4,
          "confidence": 1.0
        }
      ],
      "line_size": 4,
      "containing_box": null,
      "frame": null,
      "text_payload": ""
    }
  ],
  "import_fname": "1596490801_sarah_peterson.json"
}