{
  "task_meta": {},
  "annotations": [
    {
      "id": "f89186f5-8d7f-4c88-b40c-0e4d67192fb6",
      "new": false,
      "parent_id": null,
      "created_by": "brett_norling",
      "created_at": "2021-05-28T20:02:31.053Z",
      "deprecated": false,
      "spatial_type": "tbar",
      "spatial_payload": [
        [
          363.08899167437556,
          386.936540240518
        ],
        [
          365.83607770582796,
          384.9472710453284
        ]
      ],
      "classification_payloads": [
        {
          "class_id": 6,
          "confidence": 1
        }
      ],
      "line_size": 1.5157292392453923,
      "containing_box": {
        "tlx": 358.5418039566394,
        "tly": 380.40008332759226,
        "brx": 370.3832654235641,
        "bry": 391.4837279582542,
        "tlz": 4,
        "brz": 4
      },
      "frame": 24,
      "text_payload": "",
      "annotation_meta": {}
    },
    {
      "id": "2b8798cf-0cbe-4c8c-b17e-7d37250b8fce",
      "new": false,
      "parent_id": null,
      "created_by": "brett_norling",
      "created_at": "2021-05-28T20:02:33.193Z",
      "deprecated": true,
      "spatial_type": "tbar",
      "spatial_payload": [
        [
          341.3017576318224,
          371.49602220166514
        ],
        [
          341.01757631822386,
          369.12784458834415
        ]
      ],
      "classification_payloads": [
        {
          "class_id": 6,
          "confidence": 1
        }
      ],
      "line_size": 1.5157292392453923,
      "containing_box": {
        "tlx": 336.4703886004877,
        "tly": 364.580656870608,
        "brx": 345.84894534955856,
        "bry": 376.0432099194013
      },
      "frame": 24,
      "text_payload": "",
      "annotation_meta": {}
    },
    {
      "id": "e014bcd6-c092-40ea-b7ff-08072cc24257",
      "new": false,
      "parent_id": null,
      "created_by": "brett_norling",
      "created_at": "2021-05-28T20:02:34.831Z",
      "deprecated": true,
      "spatial_type": "tbar",
      "spatial_payload": [
        [
          320.36703766546475,
          396.5039598795749
        ],
        [
          316.9568619022825,
          395.5566888342465
        ]
      ],
      "classification_payloads": [
        {
          "class_id": 6,
          "confidence": 1
        }
      ],
      "line_size": 1.5157292392453923,
      "containing_box": {
        "tlx": 312.40967418454636,
        "tly": 391.0095011165103,
        "brx": 324.9142253832009,
        "bry": 401.05114759731106
      },
      "frame": 24,
      "text_payload": "",
      "annotation_meta": {}
    },
    {
      "id": "5793d780-cdcf-4b36-98d4-43eb68aaea0b",
      "new": false,
      "parent_id": null,
      "created_by": "brett_norling",
      "created_at": "2021-05-28T20:02:38.265Z",
      "deprecated": false,
      "spatial_type": "tbar",
      "spatial_payload": [
        [
          336.5654024051804,
          426.0825161887142
        ],
        [
          335.5234042553191,
          427.8823311748381
        ]
      ],
      "classification_payloads": [
        {
          "class_id": 6,
          "confidence": 1
        }
      ],
      "line_size": 1.5157292392453923,
      "containing_box": {
        "tlx": 330.97621653758296,
        "tly": 421.535328470978,
        "brx": 341.1125901229166,
        "bry": 432.42951889257427,
        "tlz": 4,
        "brz": 4
      },
      "frame": 24,
      "text_payload": "",
      "annotation_meta": {}
    },
    {
      "id": "3b0b5a17-2210-40a5-b6c9-e1d5043bbd16",
      "new": false,
      "parent_id": null,
      "created_by": "brett_norling",
      "created_at": "2021-05-28T20:02:39.885Z",
      "deprecated": false,
      "spatial_type": "tbar",
      "spatial_payload": [
        [
          373.22477991354947,
          421.2513801012594
        ],
        [
          375.21404910873906,
          422.8617408783176
        ]
      ],
      "classification_payloads": [
        {
          "class_id": 6,
          "confidence": 1
        }
      ],
      "line_size": 1.5157292392453923,
      "containing_box": {
        "tlx": 368.6775921958133,
        "tly": 416.7041923835232,
        "brx": 379.7612368264752,
        "bry": 427.4089285960538,
        "tlz": 4,
        "brz": 4
      },
      "frame": 24,
      "text_payload": "",
      "annotation_meta": {}
    },
    {
      "id": "06f4a22a-e631-4b7d-90df-151b2c76288a",
      "new": false,
      "parent_id": null,
      "created_by": "brett_norling",
      "created_at": "2021-05-28T20:02:44.850Z",
      "deprecated": false,
      "spatial_type": "tbar",
      "spatial_payload": [
        [
          376.6349676225717,
          407.32654949121184
        ],
        [
          378.4347826086956,
          407.13709528214616
        ]
      ],
      "classification_payloads": [
        {
          "class_id": 6,
          "confidence": 1
        }
      ],
      "line_size": 1.5157292392453923,
      "containing_box": {
        "tlx": 372.08777990483554,
        "tly": 402.58990756441,
        "brx": 382.9819703264318,
        "bry": 411.873737208948,
        "tlz": 5,
        "brz": 5
      },
      "frame": 25,
      "text_payload": "",
      "annotation_meta": {}
    },
    {
      "id": "2f8f542b-7ac9-4a5b-93bf-23224be6d752",
      "new": false,
      "parent_id": null,
      "created_by": "brett_norling",
      "created_at": "2021-05-28T20:02:46.561Z",
      "deprecated": true,
      "spatial_type": "tbar",
      "spatial_payload": [
        [
          354.0899167437558,
          376.8244218316374
        ],
        [
          354.3740980573543,
          375.78242368177615
        ]
      ],
      "classification_payloads": [
        {
          "class_id": 6,
          "confidence": 1
        }
      ],
      "line_size": 1.5157292392453923,
      "containing_box": {
        "tlx": 349.54272902601963,
        "tly": 371.23523596404,
        "brx": 358.92128577509044,
        "bry": 381.37160954937355
      },
      "frame": 25,
      "text_payload": "",
      "annotation_meta": {}
    },
    {
      "id": "449bdf7e-a80a-4d55-8300-6fb7e2fcdab1",
      "new": false,
      "parent_id": null,
      "created_by": "brett_norling",
      "created_at": "2021-05-28T20:02:48.068Z",
      "deprecated": true,
      "spatial_type": "tbar",
      "spatial_payload": [
        [
          323.20888066604994,
          390.8440333024977
        ],
        [
          321.31433857539315,
          389.80203515263645
        ]
      ],
      "classification_payloads": [
        {
          "class_id": 6,
          "confidence": 1
        }
      ],
      "line_size": 1.5157292392453923,
      "containing_box": {
        "tlx": 316.767150857657,
        "tly": 385.2548474349003,
        "brx": 327.7560683837861,
        "bry": 395.39122102023384
      },
      "frame": 25,
      "text_payload": "",
      "annotation_meta": {}
    },
    {
      "id": "78b1644f-3c1c-47f7-889b-744b6ab23f33",
      "new": false,
      "parent_id": null,
      "created_by": "brett_norling",
      "created_at": "2021-05-28T20:02:49.470Z",
      "deprecated": false,
      "spatial_type": "tbar",
      "spatial_payload": [
        [
          333.53413506012953,
          426.55615171137833
        ],
        [
          332.30268270120257,
          427.97705827937097
        ]
      ],
      "classification_payloads": [
        {
          "class_id": 6,
          "confidence": 1
        }
      ],
      "line_size": 1.5157292392453923,
      "containing_box": {
        "tlx": 327.7554949834664,
        "tly": 422.00896399364217,
        "brx": 338.0813227778657,
        "bry": 432.52424599710713,
        "tlz": 5,
        "brz": 5
      },
      "frame": 25,
      "text_payload": "",
      "annotation_meta": {}
    },
    {
      "id": "e9dd8d22-21b8-4f43-abd5-30f886a372d4",
      "new": false,
      "parent_id": null,
      "created_by": "brett_norling",
      "created_at": "2021-05-28T20:02:52.605Z",
      "deprecated": false,
      "spatial_type": "tbar",
      "spatial_payload": [
        [
          374.83515263644773,
          419.7358001850139
        ],
        [
          376.2560592044403,
          420.872525439408
        ]
      ],
      "classification_payloads": [
        {
          "class_id": 6,
          "confidence": 1
        }
      ],
      "line_size": 1.5157292392453923,
      "containing_box": {
        "tlx": 370.28796491871157,
        "tly": 415.1886124672777,
        "brx": 380.80324692217647,
        "bry": 425.41971315714414,
        "tlz": 6,
        "brz": 6
      },
      "frame": 26,
      "text_payload": "",
      "annotation_meta": {}
    },
    {
      "id": "2fe4e7c1-2e61-4b8f-a6cf-a039a330cf1b",
      "new": false,
      "parent_id": null,
      "created_by": "brett_norling",
      "created_at": "2021-05-28T20:02:53.948Z",
      "deprecated": false,
      "spatial_type": "tbar",
      "spatial_payload": [
        [
          329.36614246068456,
          425.4194264569843
        ],
        [
          328.3241443108233,
          426.4614246068455
        ]
      ],
      "classification_payloads": [
        {
          "class_id": 6,
          "confidence": 1
        }
      ],
      "line_size": 1.5157292392453923,
      "containing_box": {
        "tlx": 323.77695659308716,
        "tly": 420.87223873924813,
        "brx": 333.9133301784207,
        "bry": 431.0086123245817,
        "tlz": 6,
        "brz": 6
      },
      "frame": 26,
      "text_payload": "",
      "annotation_meta": {}
    },
    {
      "id": "0734c2d8-3e03-4296-b5af-1f0c58512821",
      "new": false,
      "parent_id": null,
      "created_by": "brett_norling",
      "created_at": "2021-05-28T20:02:56.864Z",
      "deprecated": true,
      "spatial_type": "tbar",
      "spatial_payload": [
        [
          316.10434782608695,
          401.92710453283996
        ],
        [
          314.304532839963,
          403.06382978723406
        ]
      ],
      "classification_payloads": [
        {
          "class_id": 6,
          "confidence": 1
        }
      ],
      "line_size": 1.5157292392453923,
      "containing_box": {
        "tlx": 309.7573451222268,
        "tly": 397.3799168151038,
        "brx": 320.6515355438231,
        "bry": 407.6110175049702,
        "tlz": 6,
        "brz": 6
      },
      "frame": 26,
      "text_payload": "",
      "annotation_meta": {}
    },
    {
      "id": "24603c5f-b501-4676-b9ed-c19c837a024d",
      "new": false,
      "parent_id": null,
      "created_by": "brett_norling",
      "created_at": "2021-05-28T20:02:58.458Z",
      "deprecated": true,
      "spatial_type": "tbar",
      "spatial_payload": [
        [
          317.80943570767806,
          377.58223866790007
        ],
        [
          316.10434782608695,
          376.06660499537463
        ]
      ],
      "classification_payloads": [
        {
          "class_id": 6,
          "confidence": 1
        }
      ],
      "line_size": 1.5157292392453923,
      "containing_box": {
        "tlx": 311.5571601083508,
        "tly": 371.51941727763847,
        "brx": 322.3566234254142,
        "bry": 382.12942638563624,
        "tlz": 6,
        "brz": 6
      },
      "frame": 26,
      "text_payload": "",
      "annotation_meta": {}
    },
    {
      "id": "92d5296a-e5e2-4501-96b7-b6c424def1dd",
      "new": false,
      "parent_id": null,
      "created_by": "brett_norling",
      "created_at": "2021-05-28T20:03:00.483Z",
      "deprecated": false,
      "spatial_type": "tbar",
      "spatial_payload": [
        [
          352.85846438482884,
          373.50897317298796
        ],
        [
          353.9004625346901,
          372.27752081406106
        ]
      ],
      "classification_payloads": [
        {
          "class_id": 6,
          "confidence": 1
        }
      ],
      "line_size": 1.5157292392453923,
      "containing_box": {
        "tlx": 348.31127666709267,
        "tly": 367.7303330963249,
        "brx": 358.4476502524263,
        "bry": 378.05616089072413,
        "tlz": 6,
        "brz": 6
      },
      "frame": 26,
      "text_payload": "",
      "annotation_meta": {}
    },
    {
      "id": "347cee04-82ed-461a-ac2f-c565132715bf",
      "new": false,
      "parent_id": null,
      "created_by": "brett_norling",
      "created_at": "2021-05-28T20:03:02.439Z",
      "deprecated": false,
      "spatial_type": "tbar",
      "spatial_payload": [
        [
          372.0880666049954,
          392.9280296022202
        ],
        [
          373.69842738205364,
          392.454394079556
        ]
      ],
      "classification_payloads": [
        {
          "class_id": 6,
          "confidence": 1
        }
      ],
      "line_size": 1.5157292392453923,
      "containing_box": {
        "tlx": 367.5408788872592,
        "tly": 387.9072063618198,
        "brx": 378.2456150997898,
        "bry": 397.47521731995636,
        "tlz": 6,
        "brz": 6
      },
      "frame": 26,
      "text_payload": "",
      "annotation_meta": {}
    },
    {
      "id": "db7abb3c-e98f-446d-bdf3-48b966ab2a58",
      "new": false,
      "parent_id": null,
      "created_by": "brett_norling",
      "created_at": "2021-05-28T20:03:36.840Z",
      "deprecated": true,
      "spatial_type": "tbar",
      "spatial_payload": [
        [
          316.4630344062001,
          400.6368219205617
        ],
        [
          313.7732155623928,
          401.68935972900806
        ]
      ],
      "classification_payloads": [
        {
          "class_id": 6,
          "confidence": 1
        }
      ],
      "line_size": 1.8712706657350524,
      "containing_box": {
        "tlx": 308.15940356518763,
        "tly": 395.02300992335654,
        "brx": 322.0768464034053,
        "bry": 407.30317172621324,
        "tlz": 4,
        "brz": 4
      },
      "frame": 24,
      "text_payload": "",
      "annotation_meta": {}
    },
    {
      "id": "b6e13899-cc5f-41c3-acc8-4df0689ad7cb",
      "new": false,
      "parent_id": null,
      "created_by": "brett_norling",
      "created_at": "2021-05-28T20:03:38.700Z",
      "deprecated": true,
      "spatial_type": "tbar",
      "spatial_payload": [
        [
          320.0884424130709,
          377.1301441985934
        ],
        [
          318.68505866847573,
          375.49286316323247
        ]
      ],
      "classification_payloads": [
        {
          "class_id": 6,
          "confidence": 1
        }
      ],
      "line_size": 1.8712706657350524,
      "containing_box": {
        "tlx": 313.07124667127056,
        "tly": 369.8790511660273,
        "brx": 325.70225441027605,
        "bry": 382.7439561957986,
        "tlz": 4,
        "brz": 4
      },
      "frame": 24,
      "text_payload": "",
      "annotation_meta": {}
    },
    {
      "id": "12932dfa-a36f-4240-810d-b4f64f6891ed",
      "new": false,
      "parent_id": null,
      "created_by": "brett_norling",
      "created_at": "2021-05-28T20:03:40.180Z",
      "deprecated": false,
      "spatial_type": "tbar",
      "spatial_payload": [
        [
          345.34934981578306,
          371.51660922021296
        ],
        [
          345.70019575193186,
          369.76237953946907
        ]
      ],
      "classification_payloads": [
        {
          "class_id": 6,
          "confidence": 1
        }
      ],
      "line_size": 1.8712706657350524,
      "containing_box": {
        "tlx": 339.7355378185779,
        "tly": 364.1485675422639,
        "brx": 351.31400774913703,
        "bry": 377.13042121741813,
        "tlz": 4,
        "brz": 4
      },
      "frame": 24,
      "text_payload": "",
      "annotation_meta": {}
    },
    {
      "id": "3468f8db-5754-431c-8f08-2d9af216dac2",
      "new": false,
      "parent_id": null,
      "created_by": "brett_norling",
      "created_at": "2021-05-28T20:03:45.443Z",
      "deprecated": true,
      "spatial_type": "tbar",
      "spatial_payload": [
        [
          313.7732155623928,
          398.64869494905196
        ],
        [
          312.36983181779766,
          399.4673354667325
        ]
      ],
      "classification_payloads": [
        {
          "class_id": 6,
          "confidence": 1
        }
      ],
      "line_size": 1.8712706657350524,
      "containing_box": {
        "tlx": 306.7560198205925,
        "tly": 393.0348829518468,
        "brx": 319.387027559598,
        "bry": 405.08114746393767,
        "tlz": 5,
        "brz": 5
      },
      "frame": 25,
      "text_payload": "",
      "annotation_meta": {}
    },
    {
      "id": "a7eb62af-b8be-4a03-ac79-d17bd72eac51",
      "new": false,
      "parent_id": null,
      "created_by": "brett_norling",
      "created_at": "2021-05-28T20:03:47.281Z",
      "deprecated": true,
      "spatial_type": "tbar",
      "spatial_payload": [
        [
          325.8189260368343,
          373.036941610191
        ],
        [
          325.2341828099196,
          371.16576328406416
        ]
      ],
      "classification_payloads": [
        {
          "class_id": 6,
          "confidence": 1
        }
      ],
      "line_size": 1.8712706657350524,
      "containing_box": {
        "tlx": 319.62037081271444,
        "tly": 365.551951286859,
        "brx": 331.43273803403946,
        "bry": 378.65075360739615,
        "tlz": 5,
        "brz": 5
      },
      "frame": 25,
      "text_payload": "",
      "annotation_meta": {}
    },
    {
      "id": "347926d8-7fd6-4d8e-baff-3db923875c30",
      "new": false,
      "parent_id": null,
      "created_by": "brett_norling",
      "created_at": "2021-05-28T20:03:49.320Z",
      "deprecated": false,
      "spatial_type": "tbar",
      "spatial_payload": [
        [
          353.18490905643915,
          374.3233767094032
        ],
        [
          354.35439551026843,
          372.33524973789343
        ]
      ],
      "classification_payloads": [
        {
          "class_id": 6,
          "confidence": 1
        }
      ],
      "line_size": 1.8712706657350524,
      "containing_box": {
        "tlx": 347.571097059234,
        "tly": 366.72143774068826,
        "brx": 359.9682075074736,
        "bry": 379.93718870660837,
        "tlz": 5,
        "brz": 5
      },
      "frame": 25,
      "text_payload": "",
      "annotation_meta": {}
    },
    {
      "id": "00a1117e-4fce-4705-b2d1-93991e56e6af",
      "new": false,
      "parent_id": null,
      "created_by": "brett_norling",
      "created_at": "2021-05-28T20:03:54.362Z",
      "deprecated": true,
      "spatial_type": "tbar",
      "spatial_payload": [
        [
          357.51200893560747,
          376.0776063901471
        ],
        [
          358.7984440348196,
          373.62168483710565
        ]
      ],
      "classification_payloads": [
        {
          "class_id": 6,
          "confidence": 1
        }
      ],
      "line_size": 1.8712706657350524,
      "containing_box": {
        "tlx": 351.8981969384023,
        "tly": 368.0078728399005,
        "brx": 364.4122560320248,
        "bry": 381.69141838735226,
        "tlz": 7,
        "brz": 7
      },
      "frame": 27,
      "text_payload": "",
      "annotation_meta": {}
    },
    {
      "id": "761f7f63-f6ba-4a14-af59-0485005835ea",
      "new": false,
      "parent_id": null,
      "created_by": "brett_norling",
      "created_at": "2021-05-28T20:03:56.236Z",
      "deprecated": true,
      "spatial_type": "tbar",
      "spatial_payload": [
        [
          321.9596207391977,
          374.0894794186373
        ],
        [
          320.55623699460256,
          372.91999296480805
        ]
      ],
      "classification_payloads": [
        {
          "class_id": 6,
          "confidence": 1
        }
      ],
      "line_size": 1.8712706657350524,
      "containing_box": {
        "tlx": 314.9424249973974,
        "tly": 367.30618096760287,
        "brx": 327.5734327364029,
        "bry": 379.7032914158425,
        "tlz": 7,
        "brz": 7
      },
      "frame": 27,
      "text_payload": "",
      "annotation_meta": {}
    },
    {
      "id": "4318e1f5-e9ef-4b25-ac4d-c695be77a976",
      "new": false,
      "parent_id": null,
      "created_by": "brett_norling",
      "created_at": "2021-05-28T20:03:58.306Z",
      "deprecated": true,
      "spatial_type": "tbar",
      "spatial_payload": [
        [
          318.80200731385867,
          406.0164596081764
        ],
        [
          316.3460857608172,
          406.4842541897081
        ]
      ],
      "classification_payloads": [
        {
          "class_id": 6,
          "confidence": 1
        }
      ],
      "line_size": 1.8712706657350524,
      "containing_box": {
        "tlx": 310.732273763612,
        "tly": 400.4026476109712,
        "brx": 324.41581931106384,
        "bry": 412.0980661869133,
        "tlz": 7,
        "brz": 7
      },
      "frame": 27,
      "text_payload": "",
      "annotation_meta": {}
    },
    {
      "id": "4abe1c0e-6645-47b1-96ca-aa152bd806a8",
      "new": false,
      "parent_id": null,
      "created_by": "brett_norling",
      "created_at": "2021-05-28T20:04:00.094Z",
      "deprecated": false,
      "spatial_type": "tbar",
      "spatial_payload": [
        [
          345.5832471065489,
          430.34177784782514
        ],
        [
          345.5832471065489,
          432.56380211010077
        ]
      ],
      "classification_payloads": [
        {
          "class_id": 6,
          "confidence": 1
        }
      ],
      "line_size": 1.8712706657350524,
      "containing_box": {
        "tlx": 339.96943510934375,
        "tly": 424.72796585061997,
        "brx": 351.1970591037541,
        "bry": 438.17761410730594,
        "tlz": 7,
        "brz": 7
      },
      "frame": 27,
      "text_payload": "",
      "annotation_meta": {}
    },
    {
      "id": "7ecdf1a6-d98b-449e-aeec-f107dacafabd",
      "new": false,
      "parent_id": null,
      "created_by": "brett_norling",
      "created_at": "2021-05-28T20:04:01.803Z",
      "deprecated": true,
      "spatial_type": "tbar",
      "spatial_payload": [
        [
          374.8204084522806,
          411.62999458655685
        ],
        [
          376.9254840691733,
          412.4486351042373
        ]
      ],
      "classification_payloads": [
        {
          "class_id": 6,
          "confidence": 1
        }
      ],
      "line_size": 1.8712706657350524,
      "containing_box": {
        "tlx": 369.20659645507544,
        "tly": 406.0161825893517,
        "brx": 382.5392960663785,
        "bry": 418.0624471014425,
        "tlz": 7,
        "brz": 7
      },
      "frame": 27,
      "text_payload": "",
      "annotation_meta": {}
    },
    {
      "id": "af791975-3ea8-45ed-b39f-b5cc15c7b836",
      "new": false,
      "parent_id": null,
      "created_by": "brett_norling",
      "created_at": "2021-05-28T20:04:08.876Z",
      "deprecated": false,
      "spatial_type": "tbar",
      "spatial_payload": [
        [
          327.8070068385399,
          381.8080496153319
        ],
        [
          326.1697258031789,
          380.053819934588
        ]
      ],
      "classification_payloads": [
        {
          "class_id": 6,
          "confidence": 1
        }
      ],
      "line_size": 1.8712706657350524,
      "containing_box": {
        "tlx": 320.5559138059737,
        "tly": 374.4400079373828,
        "brx": 333.4208188357451,
        "bry": 387.4218616125371,
        "tlz": 8,
        "brz": 8
      },
      "frame": 28,
      "text_payload": "",
      "annotation_meta": {}
    },
    {
      "id": "ddaf0513-5854-4a48-8497-ff8b3da6b497",
      "new": false,
      "parent_id": null,
      "created_by": "brett_norling",
      "created_at": "2021-05-28T20:04:11.768Z",
      "deprecated": false,
      "spatial_type": "tbar",
      "spatial_payload": [
        [
          324.2985936468562,
          416.19099175649103
        ],
        [
          321.6087748030489,
          417.9452214372349
        ]
      ],
      "classification_payloads": [
        {
          "class_id": 6,
          "confidence": 1
        }
      ],
      "line_size": 1.8712706657350524,
      "containing_box": {
        "tlx": 315.9949628058437,
        "tly": 410.57717975928585,
        "brx": 329.9124056440614,
        "bry": 423.5590334344401,
        "tlz": 8,
        "brz": 8
      },
      "frame": 28,
      "text_payload": "",
      "annotation_meta": {}
    },
    {
      "id": "496f6d39-42b0-4e8c-955e-f5fe8b8d3fc2",
      "new": false,
      "parent_id": null,
      "created_by": "brett_norling",
      "created_at": "2021-05-28T20:04:14.329Z",
      "deprecated": false,
      "spatial_type": "tbar",
      "spatial_payload": [
        [
          368.62214178943657,
          417.9452214372349
        ],
        [
          370.6102687609463,
          419.46555382721294
        ]
      ],
      "classification_payloads": [
        {
          "class_id": 6,
          "confidence": 1
        }
      ],
      "line_size": 1.8712706657350524,
      "containing_box": {
        "tlx": 363.0083297922314,
        "tly": 412.33140944002974,
        "brx": 376.2240807581515,
        "bry": 425.0793658244181,
        "tlz": 8,
        "brz": 8
      },
      "frame": 28,
      "text_payload": "",
      "annotation_meta": {}
    },
    {
      "id": "17c5e09f-e6d2-4ff6-9669-89d1ea0f591e",
      "new": false,
      "parent_id": null,
      "created_by": "brett_norling",
      "created_at": "2021-05-28T20:04:17.484Z",
      "deprecated": false,
      "spatial_type": "tbar",
      "spatial_payload": [
        [
          366.9848780677521,
          390.579215332728
        ],
        [
          368.739107748496,
          389.4097288788987
        ]
      ],
      "classification_payloads": [
        {
          "class_id": 6,
          "confidence": 1
        }
      ],
      "line_size": 1.8712706657350524,
      "containing_box": {
        "tlx": 361.37106607054693,
        "tly": 383.79591688169353,
        "brx": 374.3529197457012,
        "bry": 396.19302732993316,
        "tlz": 8,
        "brz": 8
      },
      "frame": 28,
      "text_payload": "",
      "annotation_meta": {}
    },
    {
      "id": "4229bcb3-c7a6-4b11-8c81-9af2b983bc9d",
      "new": false,
      "parent_id": null,
      "created_by": "brett_norling",
      "created_at": "2021-05-28T20:04:20.132Z",
      "deprecated": false,
      "spatial_type": "tbar",
      "spatial_payload": [
        [
          353.7696522833538,
          377.7148874255081
        ],
        [
          354.35439551026843,
          375.96065774476415
        ]
      ],
      "classification_payloads": [
        {
          "class_id": 6,
          "confidence": 1
        }
      ],
      "line_size": 1.8712706657350524,
      "containing_box": {
        "tlx": 348.15584028614865,
        "tly": 370.346845747559,
        "brx": 359.9682075074736,
        "bry": 383.32869942271327,
        "tlz": 8,
        "brz": 8
      },
      "frame": 28,
      "text_payload": "",
      "annotation_meta": {}
    },
    {
      "id": "a7df50e9-bec6-4d66-a4ed-1d1deac56f61",
      "new": false,
      "parent_id": null,
      "created_by": "brett_norling",
      "created_at": "2021-05-28T20:04:30.911Z",
      "deprecated": true,
      "spatial_type": "tbar",
      "spatial_payload": [
        [
          330.3799232067684,
          384.6148575031008
        ],
        [
          328.9765394621733,
          383.4453710492715
        ]
      ],
      "classification_payloads": [
        {
          "class_id": 6,
          "confidence": 1
        }
      ],
      "line_size": 1.8712706657350524,
      "containing_box": {
        "tlx": 323.36272746496815,
        "tly": 377.8315590520663,
        "brx": 335.9937352039736,
        "bry": 390.22866950030595
      },
      "frame": 29,
      "text_payload": "",
      "annotation_meta": {}
    },
    {
      "id": "216f754d-a468-47cb-a992-2ff5e4513855",
      "new": false,
      "parent_id": null,
      "created_by": "brett_norling",
      "created_at": "2021-05-28T20:04:32.447Z",
      "deprecated": false,
      "spatial_type": "tbar",
      "spatial_payload": [
        [
          325.2341828099196,
          403.0927434736032
        ],
        [
          323.59690177455866,
          403.3266407643691
        ]
      ],
      "classification_payloads": [
        {
          "class_id": 6,
          "confidence": 1
        }
      ],
      "line_size": 1.8712706657350524,
      "containing_box": {
        "tlx": 317.9830897773535,
        "tly": 397.47893147639803,
        "brx": 330.8479948071248,
        "bry": 408.94045276157425,
        "tlz": 9,
        "brz": 9
      },
      "frame": 29,
      "text_payload": "",
      "annotation_meta": {}
    },
    {
      "id": "6b0a5b8d-4058-439e-afac-927038de3f89",
      "new": false,
      "parent_id": null,
      "created_by": "brett_norling",
      "created_at": "2021-05-28T20:04:34.173Z",
      "deprecated": false,
      "spatial_type": "tbar",
      "spatial_payload": [
        [
          335.64261224900014,
          422.7401158979349
        ],
        [
          335.05786902208547,
          424.4943455786788
        ]
      ],
      "classification_payloads": [
        {
          "class_id": 6,
          "confidence": 1
        }
      ],
      "line_size": 1.8712706657350524,
      "containing_box": {
        "tlx": 329.4440570248803,
        "tly": 417.12630390072974,
        "brx": 341.2564242462053,
        "bry": 430.108157575884,
        "tlz": 9,
        "brz": 9
      },
      "frame": 29,
      "text_payload": "",
      "annotation_meta": {}
    },
    {
      "id": "52a34879-cb75-4263-a24c-bebbde08efcb",
      "new": false,
      "parent_id": null,
      "created_by": "brett_norling",
      "created_at": "2021-05-28T20:04:35.798Z",
      "deprecated": false,
      "spatial_type": "tbar",
      "spatial_payload": [
        [
          366.75095192085865,
          413.8520188488325
        ],
        [
          368.1543356654538,
          414.55371072113
        ]
      ],
      "classification_payloads": [
        {
          "class_id": 6,
          "confidence": 1
        }
      ],
      "line_size": 1.8712706657350524,
      "containing_box": {
        "tlx": 361.1371399236535,
        "tly": 408.2382068516273,
        "brx": 373.768147662659,
        "bry": 420.1675227183352,
        "tlz": 9,
        "brz": 9
      },
      "frame": 29,
      "text_payload": "",
      "annotation_meta": {}
    },
    {
      "id": "1dc64cfc-4eb5-4fed-ad37-aadfe4dd9fff",
      "new": false,
      "parent_id": null,
      "created_by": "brett_norling",
      "created_at": "2021-05-28T20:04:45.926Z",
      "deprecated": true,
      "spatial_type": "tbar",
      "spatial_payload": [
        [
          352.3662685387587,
          374.4403253547861
        ],
        [
          352.3662685387587,
          373.27083890095685
        ]
      ],
      "classification_payloads": [
        {
          "class_id": 6,
          "confidence": 1
        }
      ],
      "line_size": 1.8712706657350524,
      "containing_box": {
        "tlx": 346.7524565415535,
        "tly": 367.65702690375167,
        "brx": 357.98008053596385,
        "bry": 380.0541373519913
      },
      "frame": 29,
      "text_payload": "",
      "annotation_meta": {}
    },
    {
      "id": "d3ac930b-8531-40e4-babb-8de0c08aec2e",
      "new": false,
      "parent_id": null,
      "created_by": "brett_norling",
      "created_at": "2021-05-28T20:04:47.670Z",
      "deprecated": true,
      "spatial_type": "tbar",
      "spatial_payload": [
        [
          371.07805180002697,
          385.3165493753983
        ],
        [
          372.4814355446221,
          384.8487547938666
        ]
      ],
      "classification_payloads": [
        {
          "class_id": 6,
          "confidence": 1
        }
      ],
      "line_size": 1.8712706657350524,
      "containing_box": {
        "tlx": 365.4642398028218,
        "tly": 379.2349427966614,
        "brx": 378.0952475418273,
        "bry": 390.9303613726035
      },
      "frame": 29,
      "text_payload": "",
      "annotation_meta": {}
    },
    {
      "id": "a74a7e6b-9718-4fb3-81a7-c6a2baab67fc",
      "new": false,
      "parent_id": null,
      "created_by": "brett_norling",
      "created_at": "2021-05-28T20:05:02.770Z",
      "deprecated": true,
      "spatial_type": "tbar",
      "spatial_payload": [
        [
          323.94774771070746,
          404.49612721819835
        ],
        [
          322.8952099022611,
          405.1978190904959
        ]
      ],
      "classification_payloads": [
        {
          "class_id": 6,
          "confidence": 1
        }
      ],
      "line_size": 1.8712706657350524,
      "containing_box": {
        "tlx": 317.28139790505594,
        "tly": 398.8823152209932,
        "brx": 329.56155970791264,
        "bry": 410.8116310877011
      },
      "frame": 30,
      "text_payload": "",
      "annotation_meta": {}
    },
    {
      "id": "fa493715-fb8d-466b-9bef-41b445ec395b",
      "new": false,
      "parent_id": null,
      "created_by": "brett_norling",
      "created_at": "2021-05-28T20:05:04.598Z",
      "deprecated": true,
      "spatial_type": "tbar",
      "spatial_payload": [
        [
          355.056087382566,
          414.2028647849813
        ],
        [
          355.64083060948064,
          415.7231971749593
        ]
      ],
      "classification_payloads": [
        {
          "class_id": 6,
          "confidence": 1
        }
      ],
      "line_size": 1.8712706657350524,
      "containing_box": {
        "tlx": 349.4422753853608,
        "tly": 408.5890527877761,
        "brx": 361.2546426066858,
        "bry": 421.33700917216447
      },
      "frame": 30,
      "text_payload": "",
      "annotation_meta": {}
    },
    {
      "id": "71c867b8-8f0f-4280-91f7-79441e9540b1",
      "new": false,
      "parent_id": null,
      "created_by": "brett_norling",
      "created_at": "2021-05-28T20:05:05.941Z",
      "deprecated": true,
      "spatial_type": "tbar",
      "spatial_payload": [
        [
          374.235665225366,
          391.2809302899276
        ],
        [
          375.4051516791953,
          391.2809302899276
        ]
      ],
      "classification_payloads": [
        {
          "class_id": 6,
          "confidence": 1
        }
      ],
      "line_size": 1.8712706657350524,
      "containing_box": {
        "tlx": 368.62185322816083,
        "tly": 385.6671182927224,
        "brx": 381.01896367640046,
        "bry": 396.8947422871328
      },
      "frame": 30,
      "text_payload": "",
      "annotation_meta": {}
    },
    {
      "id": "3b991a06-89e6-42d7-91e1-41a950c86c3f",
      "new": false,
      "parent_id": null,
      "created_by": "brett_norling",
      "created_at": "2021-05-28T20:05:07.863Z",
      "deprecated": true,
      "spatial_type": "tbar",
      "spatial_payload": [
        [
          358.0967521625221,
          368.242047149491
        ],
        [
          358.0967521625221,
          366.8386634048959
        ]
      ],
      "classification_payloads": [
        {
          "class_id": 6,
          "confidence": 1
        }
      ],
      "line_size": 1.8712706657350524,
      "containing_box": {
        "tlx": 352.4829401653169,
        "tly": 361.2248514076907,
        "brx": 363.71056415972726,
        "bry": 373.85585914669616
      },
      "frame": 30,
      "text_payload": "",
      "annotation_meta": {}
    },
    {
      "id": "36d57576-a426-4ac4-8b75-904fc57ca378",
      "new": false,
      "parent_id": null,
      "created_by": "brett_norling",
      "created_at": "2021-05-28T20:05:09.365Z",
      "deprecated": true,
      "spatial_type": "tbar",
      "spatial_payload": [
        [
          330.61374547160256,
          380.0538603331666
        ],
        [
          329.67815630853914,
          378.5335279431886
        ]
      ],
      "classification_payloads": [
        {
          "class_id": 6,
          "confidence": 1
        }
      ],
      "line_size": 1.8712706657350524,
      "containing_box": {
        "tlx": 324.06434431133397,
        "tly": 372.9197159459834,
        "brx": 336.22755746880773,
        "bry": 385.6676723303718,
        "tlz": 10,
        "brz": 10
      },
      "frame": 30,
      "text_payload": "",
      "annotation_meta": {}
    },
    {
      "id": "a6940eae-6c5c-4ab5-8934-5864e7c00437",
      "new": false,
      "parent_id": null,
      "created_by": "brett_norling",
      "created_at": "2021-05-28T20:06:14.174Z",
      "deprecated": false,
      "spatial_type": "tbar",
      "spatial_payload": [
        [
          345.70019575193186,
          382.2758845954422
        ],
        [
          345.70019575193186,
          380.7555522054642
        ]
      ],
      "classification_payloads": [
        {
          "class_id": 6,
          "confidence": 1
        }
      ],
      "line_size": 1.8712706657350524,
      "containing_box": {
        "tlx": 340.0863837547267,
        "tly": 375.141740208259,
        "brx": 351.31400774913703,
        "bry": 387.8896965926474,
        "tlz": 9,
        "brz": 9
      },
      "frame": 29,
      "text_payload": "",
      "annotation_meta": {}
    },
    {
      "id": "4e8acce9-844e-4550-aeef-18e5ff61ca34",
      "new": false,
      "parent_id": null,
      "created_by": "brett_norling",
      "created_at": "2021-05-28T20:06:16.339Z",
      "deprecated": false,
      "spatial_type": "tbar",
      "spatial_payload": [
        [
          360.55267371556357,
          392.4504167437569
        ],
        [
          362.65774933245626,
          391.16398164454466
        ]
      ],
      "classification_payloads": [
        {
          "class_id": 6,
          "confidence": 1
        }
      ],
      "line_size": 1.8712706657350524,
      "containing_box": {
        "tlx": 354.9388617183584,
        "tly": 385.5501696473395,
        "brx": 368.27156132966144,
        "bry": 398.06422874096205,
        "tlz": 9,
        "brz": 9
      },
      "frame": 29,
      "text_payload": "",
      "annotation_meta": {}
    },
    {
      "id": "3ce60465-4adb-43a6-a9ad-3a0d0e0c8da6",
      "new": false,
      "parent_id": null,
      "created_by": "brett_norling",
      "created_at": "2021-05-28T20:06:19.521Z",
      "deprecated": true,
      "spatial_type": "tbar",
      "spatial_payload": [
        [
          337.74768786589283,
          398.2978490129032
        ],
        [
          337.16294463897816,
          400.0520786936471
        ]
      ],
      "classification_payloads": [
        {
          "class_id": 6,
          "confidence": 1
        }
      ],
      "line_size": 1.8712706657350524,
      "containing_box": {
        "tlx": 331.549132641773,
        "tly": 392.68403701569804,
        "brx": 343.361499863098,
        "bry": 405.6658906908523,
        "tlz": 10,
        "brz": 10
      },
      "frame": 30,
      "text_payload": "",
      "annotation_meta": {}
    },
    {
      "id": "ea2c2c52-bf02-4236-8622-c8df5a42d771",
      "new": false,
      "parent_id": null,
      "created_by": "brett_norling",
      "created_at": "2021-05-28T20:06:20.846Z",
      "deprecated": true,
      "spatial_type": "tbar",
      "spatial_payload": [
        [
          359.61708455250016,
          394.7893896514154
        ],
        [
          361.1374169424782,
          395.37413287833004
        ]
      ],
      "classification_payloads": [
        {
          "class_id": 6,
          "confidence": 1
        }
      ],
      "line_size": 1.8712706657350524,
      "containing_box": {
        "tlx": 354.003272555295,
        "tly": 389.1755776542102,
        "brx": 366.75122893968336,
        "bry": 400.9879448755352,
        "tlz": 10,
        "brz": 10
      },
      "frame": 30,
      "text_payload": "",
      "annotation_meta": {}
    },
    {
      "id": "bf9264b7-d60d-46de-803c-1f64a3b23c82",
      "new": false,
      "parent_id": null,
      "created_by": "brett_norling",
      "created_at": "2021-05-28T20:06:22.264Z",
      "deprecated": true,
      "spatial_type": "tbar",
      "spatial_payload": [
        [
          359.26623861635136,
          375.49286316323247
        ],
        [
          360.3187764247977,
          374.3233767094032
        ]
      ],
      "classification_payloads": [
        {
          "class_id": 6,
          "confidence": 1
        }
      ],
      "line_size": 1.8712706657350524,
      "containing_box": {
        "tlx": 353.6524266191462,
        "tly": 368.709564712198,
        "brx": 365.9325884220029,
        "bry": 381.10667516043765,
        "tlz": 10,
        "brz": 10
      },
      "frame": 30,
      "text_payload": "",
      "annotation_meta": {}
    },
    {
      "id": "8d9365f6-9aa0-4c26-a506-2f1251881d30",
      "new": false,
      "parent_id": null,
      "created_by": "brett_norling",
      "created_at": "2021-05-28T20:06:34.760Z",
      "deprecated": false,
      "spatial_type": "tbar",
      "spatial_payload": [
        [
          354.12049821950257,
          426.3655239048056
        ],
        [
          354.47134415565137,
          428.00280494016664
        ]
      ],
      "classification_payloads": [
        {
          "class_id": 6,
          "confidence": 1
        }
      ],
      "line_size": 1.8712706657350524,
      "containing_box": {
        "tlx": 348.5066862222974,
        "tly": 420.75171190760045,
        "brx": 360.08515615285654,
        "bry": 433.6166169373718,
        "tlz": 3,
        "brz": 3
      },
      "frame": 23,
      "text_payload": "",
      "annotation_meta": {}
    },
    {
      "id": "164be2ae-94d8-40a0-b381-45350294e274",
      "new": false,
      "parent_id": null,
      "created_by": "brett_norling",
      "created_at": "2021-05-28T20:06:37.347Z",
      "deprecated": false,
      "spatial_type": "tbar",
      "spatial_payload": [
        [
          353.3018577018221,
          381.2233467869959
        ],
        [
          354.12049821950257,
          379.5860657516349
        ]
      ],
      "classification_payloads": [
        {
          "class_id": 6,
          "confidence": 1
        }
      ],
      "line_size": 1.8712706657350524,
      "containing_box": {
        "tlx": 347.6880457046169,
        "tly": 373.97225375442974,
        "brx": 359.73431021670774,
        "bry": 386.83715878420105,
        "tlz": 3,
        "brz": 3
      },
      "frame": 23,
      "text_payload": "",
      "annotation_meta": {}
    },
    {
      "id": "f4a7139b-6431-4ff3-9620-223d81d32cb8",
      "new": false,
      "parent_id": null,
      "created_by": "brett_norling",
      "created_at": "2021-05-28T20:06:39.144Z",
      "deprecated": true,
      "spatial_type": "tbar",
      "spatial_payload": [
        [
          328.15790471571836,
          384.4978626879137
        ],
        [
          326.1697777442086,
          383.67922217023323
        ]
      ],
      "classification_payloads": [
        {
          "class_id": 6,
          "confidence": 1
        }
      ],
      "line_size": 1.8712706657350524,
      "containing_box": {
        "tlx": 320.5559657470034,
        "tly": 378.06541017302806,
        "brx": 333.77171671292353,
        "bry": 390.1116746851189
      },
      "frame": 23,
      "text_payload": "",
      "annotation_meta": {}
    },
    {
      "id": "7cb86cca-705f-4d76-937b-d8570fc4669a",
      "new": false,
      "parent_id": null,
      "created_by": "brett_norling",
      "created_at": "2021-05-28T20:06:40.832Z",
      "deprecated": true,
      "spatial_type": "tbar",
      "spatial_payload": [
        [
          322.7782612568782,
          410.3435594873447
        ],
        [
          321.2579288669001,
          411.04525135964224
        ]
      ],
      "classification_payloads": [
        {
          "class_id": 6,
          "confidence": 1
        }
      ],
      "line_size": 1.8712706657350524,
      "containing_box": {
        "tlx": 315.6441168696949,
        "tly": 404.7297474901395,
        "brx": 328.39207325408336,
        "bry": 416.6590633568474,
        "tlz": 3,
        "brz": 3
      },
      "frame": 23,
      "text_payload": "",
      "annotation_meta": {}
    },
    {
      "id": "778e34e9-d526-49b5-99b1-36d3a60242f6",
      "new": false,
      "parent_id": null,
      "created_by": "brett_norling",
      "created_at": "2021-05-28T20:06:49.366Z",
      "deprecated": true,
      "spatial_type": "tbar",
      "spatial_payload": [
        [
          313.1884723354782,
          386.01824124769587
        ],
        [
          312.0189858816489,
          385.43349802078126
        ]
      ],
      "classification_payloads": [
        {
          "class_id": 6,
          "confidence": 1
        }
      ],
      "line_size": 1.8712706657350524,
      "containing_box": {
        "tlx": 306.40517388444374,
        "tly": 379.8196860235761,
        "brx": 318.80228433268337,
        "bry": 391.63205324490104,
        "tlz": 3,
        "brz": 3
      },
      "frame": 23,
      "text_payload": "",
      "annotation_meta": {}
    },
    {
      "id": "cae53ec5-42b1-4ef9-aad6-e81d19da851f",
      "new": false,
      "parent_id": null,
      "created_by": "brett_norling",
      "created_at": "2021-05-28T20:06:51.783Z",
      "deprecated": true,
      "spatial_type": "tbar",
      "spatial_payload": [
        [
          332.4849988236611,
          373.62168483710565
        ],
        [
          332.36805017827817,
          371.51660922021296
        ]
      ],
      "classification_payloads": [
        {
          "class_id": 6,
          "confidence": 1
        }
      ],
      "line_size": 1.8712706657350524,
      "containing_box": {
        "tlx": 326.754238181073,
        "tly": 365.9027972230078,
        "brx": 338.0988108208663,
        "bry": 379.2354968343108,
        "tlz": 3,
        "brz": 3
      },
      "frame": 23,
      "text_payload": "",
      "annotation_meta": {}
    },
    {
      "id": "13d03761-612d-4770-9543-2b8b110dea50",
      "new": false,
      "parent_id": null,
      "created_by": "brett_norling",
      "created_at": "2021-05-28T20:06:59.777Z",
      "deprecated": false,
      "spatial_type": "tbar",
      "spatial_payload": [
        [
          366.283157339327,
          393.61990319758615
        ],
        [
          368.1543356654538,
          392.91821132528855
        ]
      ],
      "classification_payloads": [
        {
          "class_id": 6,
          "confidence": 1
        }
      ],
      "line_size": 1.8712706657350524,
      "containing_box": {
        "tlx": 360.6693453421218,
        "tly": 387.3043993280834,
        "brx": 373.768147662659,
        "bry": 399.23371519479133,
        "tlz": 3,
        "brz": 3
      },
      "frame": 23,
      "text_payload": "",
      "annotation_meta": {}
    },
    {
      "id": "244ebca0-f388-449e-80e1-d02bc395a21c",
      "new": false,
      "parent_id": null,
      "created_by": "brett_norling",
      "created_at": "2021-05-28T20:07:15.669Z",
      "deprecated": true,
      "spatial_type": "tbar",
      "spatial_payload": [
        [
          326.28672061836596,
          377.0131955532105
        ],
        [
          326.28672061836596,
          376.0776063901471
        ]
      ],
      "classification_payloads": [
        {
          "class_id": 6,
          "confidence": 1
        }
      ],
      "line_size": 1.8712706657350524,
      "containing_box": {
        "tlx": 320.6729086211608,
        "tly": 370.4637943929419,
        "brx": 331.90053261557114,
        "bry": 382.62700755041567,
        "tlz": 1,
        "brz": 1
      },
      "frame": 21,
      "text_payload": "",
      "annotation_meta": {}
    },
    {
      "id": "2c9f8c35-825b-4f30-8ff0-fd97fa50e097",
      "new": false,
      "parent_id": null,
      "created_by": "brett_norling",
      "created_at": "2021-05-28T20:07:17.266Z",
      "deprecated": true,
      "spatial_type": "tbar",
      "spatial_payload": [
        [
          312.36983181779766,
          393.9707491337349
        ],
        [
          311.20034536396844,
          394.55549236064957
        ]
      ],
      "classification_payloads": [
        {
          "class_id": 6,
          "confidence": 1
        }
      ],
      "line_size": 1.8712706657350524,
      "containing_box": {
        "tlx": 305.58653336676326,
        "tly": 388.3569371365297,
        "brx": 317.98364381500284,
        "bry": 400.16930435785474,
        "tlz": 1,
        "brz": 1
      },
      "frame": 21,
      "text_payload": "",
      "annotation_meta": {}
    },
    {
      "id": "f375ee82-3fa4-40b8-83ef-ca262169ce65",
      "new": false,
      "parent_id": null,
      "created_by": "brett_norling",
      "created_at": "2021-05-28T20:07:19.603Z",
      "deprecated": true,
      "spatial_type": "tbar",
      "spatial_payload": [
        [
          328.8595908167904,
          406.0164596081764
        ],
        [
          328.39179623525865,
          406.83510012585685
        ]
      ],
      "classification_payloads": [
        {
          "class_id": 6,
          "confidence": 1
        }
      ],
      "line_size": 1.8712706657350524,
      "containing_box": {
        "tlx": 322.7779842380535,
        "tly": 400.4026476109712,
        "brx": 334.47340281399556,
        "bry": 412.44891212306203
      },
      "frame": 21,
      "text_payload": "",
      "annotation_meta": {}
    },
    {
      "id": "5688449c-ab58-477a-b1c4-b66da2822470",
      "new": false,
      "parent_id": null,
      "created_by": "brett_norling",
      "created_at": "2021-05-28T20:07:42.077Z",
      "deprecated": true,
      "spatial_type": "tbar",
      "spatial_payload": [
        [
          308.74439495479936,
          389.40971156522215
        ],
        [
          307.57490850097014,
          388.82496833830754
        ]
      ],
      "classification_payloads": [
        {
          "class_id": 6,
          "confidence": 1
        }
      ],
      "line_size": 1.8712706657350524,
      "containing_box": {
        "tlx": 301.96109650376496,
        "tly": 383.21115634110237,
        "brx": 314.35820695200454,
        "bry": 395.02352356242733,
        "tlz": 2,
        "brz": 2
      },
      "frame": 22,
      "text_payload": "",
      "annotation_meta": {}
    },
    {
      "id": "2abc19d6-3396-4e13-af5c-fc10ab9ae846",
      "new": false,
      "parent_id": null,
      "created_by": "brett_norling",
      "created_at": "2021-05-28T20:07:45.721Z",
      "deprecated": true,
      "spatial_type": "tbar",
      "spatial_payload": [
        [
          327.22236749368454,
          378.0656871918527
        ],
        [
          327.22236749368454,
          377.01314938340636
        ]
      ],
      "classification_payloads": [
        {
          "class_id": 6,
          "confidence": 1
        }
      ],
      "line_size": 1.8712706657350524,
      "containing_box": {
        "tlx": 321.60855549647937,
        "tly": 371.3993373862012,
        "brx": 332.8361794908897,
        "bry": 383.6794991890579,
        "tlz": 2,
        "brz": 2
      },
      "frame": 22,
      "text_payload": "",
      "annotation_meta": {}
    },
    {
      "id": "9cdf7f17-e13b-4321-affe-0b90401040fc",
      "new": false,
      "parent_id": null,
      "created_by": "brett_norling",
      "created_at": "2021-05-28T20:07:48.204Z",
      "deprecated": true,
      "spatial_type": "tbar",
      "spatial_payload": [
        [
          348.5069632411221,
          381.45724407776174
        ],
        [
          350.261192921866,
          379.70301439701785
        ]
      ],
      "classification_payloads": [
        {
          "class_id": 6,
          "confidence": 1
        }
      ],
      "line_size": 1.8712706657350524,
      "containing_box": {
        "tlx": 342.8931512439169,
        "tly": 374.0892023998127,
        "brx": 355.87500491907116,
        "bry": 387.0710560749669,
        "tlz": 2,
        "brz": 2
      },
      "frame": 22,
      "text_payload": "",
      "annotation_meta": {}
    },
    {
      "id": "57d92be6-43fa-4825-90bf-27708d001b8c",
      "new": false,
      "parent_id": null,
      "created_by": "brett_norling",
      "created_at": "2021-05-28T20:07:50.086Z",
      "deprecated": false,
      "spatial_type": "tbar",
      "spatial_payload": [
        [
          359.3831872617343,
          396.6605679775422
        ],
        [
          361.37131423324405,
          395.2571842329471
        ]
      ],
      "classification_payloads": [
        {
          "class_id": 6,
          "confidence": 1
        }
      ],
      "line_size": 1.8712706657350524,
      "containing_box": {
        "tlx": 353.7693752645291,
        "tly": 389.64337223574194,
        "brx": 366.9851262304492,
        "bry": 402.2743799747474,
        "tlz": 2,
        "brz": 2
      },
      "frame": 22,
      "text_payload": "",
      "annotation_meta": {}
    },
    {
      "id": "8d822242-1861-4654-af31-30c51a131649",
      "new": false,
      "parent_id": null,
      "created_by": "brett_norling",
      "created_at": "2021-05-28T20:07:51.964Z",
      "deprecated": false,
      "spatial_type": "tbar",
      "spatial_payload": [
        [
          365.4645168216465,
          411.7469432319398
        ],
        [
          366.8679005662416,
          412.6825323950032
        ]
      ],
      "classification_payloads": [
        {
          "class_id": 6,
          "confidence": 1
        }
      ],
      "line_size": 1.8712706657350524,
      "containing_box": {
        "tlx": 359.8507048244413,
        "tly": 406.1331312347346,
        "brx": 372.48171256344676,
        "bry": 418.29634439220837,
        "tlz": 2,
        "brz": 2
      },
      "frame": 22,
      "text_payload": "",
      "annotation_meta": {}
    },
    {
      "id": "a9020ec2-f1fc-41d4-8fad-9f50fa887444",
      "new": false,
      "parent_id": null,
      "created_by": "brett_norling",
      "created_at": "2021-05-28T20:07:53.605Z",
      "deprecated": false,
      "spatial_type": "tbar",
      "spatial_payload": [
        [
          338.9171743197221,
          415.2554025934276
        ],
        [
          338.5663283835733,
          417.12658091955444
        ]
      ],
      "classification_payloads": [
        {
          "class_id": 6,
          "confidence": 1
        }
      ],
      "line_size": 1.8712706657350524,
      "containing_box": {
        "tlx": 332.95251638636813,
        "tly": 409.64159059622244,
        "brx": 344.5309863169273,
        "bry": 422.7403929167596,
        "tlz": 2,
        "brz": 2
      },
      "frame": 22,
      "text_payload": "",
      "annotation_meta": {}
    },
    {
      "id": "155e2063-d0ae-4946-bc41-c68dd0cdfb92",
      "new": false,
      "parent_id": null,
      "created_by": "brett_norling",
      "created_at": "2021-05-28T20:07:54.954Z",
      "deprecated": true,
      "spatial_type": "tbar",
      "spatial_payload": [
        [
          317.2816749238806,
          406.601202835091
        ],
        [
          316.3460857608172,
          408.12153522506907
        ]
      ],
      "classification_payloads": [
        {
          "class_id": 6,
          "confidence": 1
        }
      ],
      "line_size": 1.8712706657350524,
      "containing_box": {
        "tlx": 310.732273763612,
        "tly": 400.9873908378858,
        "brx": 322.89548692108576,
        "bry": 413.73534722227424,
        "tlz": 2,
        "brz": 2
      },
      "frame": 22,
      "text_payload": "",
      "annotation_meta": {}
    },
    {
      "id": "08610025-8469-4f8b-bff9-2cb711856b47",
      "new": false,
      "parent_id": null,
      "created_by": "brett_norling",
      "created_at": "2021-05-28T20:08:02.207Z",
      "deprecated": true,
      "spatial_type": "tbar",
      "spatial_payload": [
        [
          343.0103769081245,
          384.14706292156905
        ],
        [
          344.06291471657084,
          382.97757646773977
        ]
      ],
      "classification_payloads": [
        {
          "class_id": 6,
          "confidence": 1
        }
      ],
      "line_size": 1.8712706657350524,
      "containing_box": {
        "tlx": 337.3965649109193,
        "tly": 377.3637644705346,
        "brx": 349.676726713776,
        "bry": 389.7608749187742
      },
      "frame": 21,
      "text_payload": "",
      "annotation_meta": {}
    },
    {
      "id": "7e708e79-8308-4c7c-8319-96d179c1a26b",
      "new": false,
      "parent_id": null,
      "created_by": "brett_norling",
      "created_at": "2021-05-28T20:08:03.800Z",
      "deprecated": true,
      "spatial_type": "tbar",
      "spatial_payload": [
        [
          348.2730659503562,
          401.68935972900806
        ],
        [
          349.9103469857172,
          400.75377056594465
        ]
      ],
      "classification_payloads": [
        {
          "class_id": 6,
          "confidence": 1
        }
      ],
      "line_size": 1.8712706657350524,
      "containing_box": {
        "tlx": 342.65925395315105,
        "tly": 395.1399585687395,
        "brx": 355.52415898292236,
        "bry": 407.30317172621324
      },
      "frame": 21,
      "text_payload": "",
      "annotation_meta": {}
    },
    {
      "id": "dd0e0923-79b2-4113-bbfc-62bd955f464a",
      "new": false,
      "parent_id": null,
      "created_by": "brett_norling",
      "created_at": "2021-05-28T20:08:05.125Z",
      "deprecated": true,
      "spatial_type": "tbar",
      "spatial_payload": [
        [
          346.986630851144,
          412.7994810403861
        ],
        [
          346.986630851144,
          414.55371072113
        ]
      ],
      "classification_payloads": [
        {
          "class_id": 6,
          "confidence": 1
        }
      ],
      "line_size": 1.8712706657350524,
      "containing_box": {
        "tlx": 341.37281885393884,
        "tly": 407.18566904318095,
        "brx": 352.6004428483492,
        "bry": 420.1675227183352
      },
      "frame": 21,
      "text_payload": "",
      "annotation_meta": {}
    },
    {
      "id": "8ff42795-723d-4046-b2f1-b4131d7bb017",
      "new": false,
      "parent_id": null,
      "created_by": "brett_norling",
      "created_at": "2021-05-28T20:08:42.459Z",
      "deprecated": true,
      "spatial_type": "tbar",
      "spatial_payload": [
        [
          342.8934282627416,
          388.3572141553544
        ],
        [
          344.06291471657084,
          388.70806009150317
        ]
      ],
      "classification_payloads": [
        {
          "class_id": 6,
          "confidence": 1
        }
      ],
      "line_size": 1.8712706657350524,
      "containing_box": {
        "tlx": 337.27961626553645,
        "tly": 382.74340215814925,
        "brx": 349.676726713776,
        "bry": 394.32187208870835,
        "tlz": 1,
        "brz": 1
      },
      "frame": 21,
      "text_payload": "",
      "annotation_meta": {}
    },
    {
      "id": "a4beb9f2-a83d-42da-b9c9-998b357093b5",
      "new": false,
      "parent_id": null,
      "created_by": "brett_norling",
      "created_at": "2021-05-28T20:08:44.837Z",
      "deprecated": true,
      "spatial_type": "tbar",
      "spatial_payload": [
        [
          328.8595908167904,
          407.65374064353733
        ],
        [
          328.8595908167904,
          409.1740730335154
        ]
      ],
      "classification_payloads": [
        {
          "class_id": 6,
          "confidence": 1
        }
      ],
      "line_size": 1.8712706657350524,
      "containing_box": {
        "tlx": 323.2457788195852,
        "tly": 402.03992864633216,
        "brx": 334.47340281399556,
        "bry": 414.7878850307206,
        "tlz": 1,
        "brz": 1
      },
      "frame": 21,
      "text_payload": "",
      "annotation_meta": {}
    },
    {
      "id": "eb05cbe8-0f2d-4ba3-be87-858fd2477fd5",
      "new": true,
      "parent_id": "ea2c2c52-bf02-4236-8622-c8df5a42d771",
      "created_by": "helle246",
      "created_at": "2021-05-28T20:06:20.846Z",
      "deprecated": true,
      "spatial_type": "tbar",
      "spatial_payload": [
        [
          359.61708455250016,
          394.7893896514154
        ],
        [
          361.1374169424782,
          395.37413287833004
        ]
      ],
      "classification_payloads": [
        {
          "class_id": 6,
          "confidence": 1
        }
      ],
      "line_size": 1.8712706657350524,
      "containing_box": {
        "tlx": 354.003272555295,
        "tly": 389.1755776542102,
        "brx": 366.75122893968336,
        "bry": 400.9879448755352,
        "tlz": 10,
        "brz": 10
      },
      "frame": 30,
      "text_payload": "",
      "annotation_meta": {}
    },
    {
      "id": "53f64cdc-df11-41f5-82a7-50a7dcea5606",
      "new": true,
      "parent_id": "bf9264b7-d60d-46de-803c-1f64a3b23c82",
      "created_by": "helle246",
      "created_at": "2021-05-28T20:06:22.264Z",
      "deprecated": true,
      "spatial_type": "tbar",
      "spatial_payload": [
        [
          359.26623861635136,
          375.49286316323247
        ],
        [
          360.3187764247977,
          374.3233767094032
        ]
      ],
      "classification_payloads": [
        {
          "class_id": 6,
          "confidence": 1
        }
      ],
      "line_size": 1.8712706657350524,
      "containing_box": {
        "tlx": 353.6524266191462,
        "tly": 368.709564712198,
        "brx": 365.9325884220029,
        "bry": 381.10667516043765,
        "tlz": 10,
        "brz": 10
      },
      "frame": 30,
      "text_payload": "",
      "annotation_meta": {}
    },
    {
      "id": "2c0cdbf8-a50a-4a16-9a84-efc284059178",
      "new": true,
      "parent_id": "36d57576-a426-4ac4-8b75-904fc57ca378",
      "created_by": "helle246",
      "created_at": "2021-05-28T20:05:09.365Z",
      "deprecated": true,
      "spatial_type": "tbar",
      "spatial_payload": [
        [
          330.61374547160256,
          380.0538603331666
        ],
        [
          329.67815630853914,
          378.5335279431886
        ]
      ],
      "classification_payloads": [
        {
          "class_id": 6,
          "confidence": 1
        }
      ],
      "line_size": 1.8712706657350524,
      "containing_box": {
        "tlx": 324.06434431133397,
        "tly": 372.9197159459834,
        "brx": 336.22755746880773,
        "bry": 385.6676723303718,
        "tlz": 10,
        "brz": 10
      },
      "frame": 30,
      "text_payload": "",
      "annotation_meta": {}
    },
    {
      "id": "b6b997e3-a450-4725-a301-811af9d2551d",
      "new": true,
      "parent_id": "3ce60465-4adb-43a6-a9ad-3a0d0e0c8da6",
      "created_by": "helle246",
      "created_at": "2021-05-28T20:06:19.521Z",
      "deprecated": true,
      "spatial_type": "tbar",
      "spatial_payload": [
        [
          337.74768786589283,
          398.2978490129032
        ],
        [
          337.16294463897816,
          400.0520786936471
        ]
      ],
      "classification_payloads": [
        {
          "class_id": 6,
          "confidence": 1
        }
      ],
      "line_size": 1.8712706657350524,
      "containing_box": {
        "tlx": 331.549132641773,
        "tly": 392.68403701569804,
        "brx": 343.361499863098,
        "bry": 405.6658906908523,
        "tlz": 10,
        "brz": 10
      },
      "frame": 30,
      "text_payload": "",
      "annotation_meta": {}
    },
    {
      "id": "232343eb-dc7d-4866-ab59-a626e373d9b1",
      "new": true,
      "parent_id": "761f7f63-f6ba-4a14-af59-0485005835ea",
      "created_by": "helle246",
      "created_at": "2021-05-28T20:03:56.236Z",
      "deprecated": false,
      "spatial_type": "tbar",
      "spatial_payload": [
        [
          326.7484830634136,
          381.1199368733372
        ],
        [
          325.3450993188184,
          379.95045041950794
        ]
      ],
      "classification_payloads": [
        {
          "class_id": 6,
          "confidence": 1
        }
      ],
      "line_size": 1.8712706657350524,
      "containing_box": {
        "tlx": 319.73128732161325,
        "tly": 374.33663842230277,
        "brx": 332.36229506061875,
        "bry": 386.7337488705424,
        "tlz": 7,
        "brz": 7
      },
      "frame": 27,
      "text_payload": "",
      "annotation_meta": {}
    },
    {
      "id": "073e81eb-ed96-446a-b303-fb579ec86ad5",
      "new": true,
      "parent_id": "4318e1f5-e9ef-4b25-ac4d-c695be77a976",
      "created_by": "helle246",
      "created_at": "2021-05-28T20:03:58.306Z",
      "deprecated": false,
      "spatial_type": "tbar",
      "spatial_payload": [
        [
          320.4322583178471,
          407.2391478611677
        ],
        [
          317.9763367648056,
          407.7069424426994
        ]
      ],
      "classification_payloads": [
        {
          "class_id": 6,
          "confidence": 1
        }
      ],
      "line_size": 1.8712706657350524,
      "containing_box": {
        "tlx": 312.3625247676004,
        "tly": 401.6253358639625,
        "brx": 326.04607031505225,
        "bry": 413.3207544399046,
        "tlz": 7,
        "brz": 7
      },
      "frame": 27,
      "text_payload": "",
      "annotation_meta": {}
    },
    {
      "id": "29abc31f-3d08-4b76-a815-fb6439624f7a",
      "new": true,
      "parent_id": "00a1117e-4fce-4705-b2d1-93991e56e6af",
      "created_by": "helle246",
      "created_at": "2021-05-28T20:03:54.362Z",
      "deprecated": false,
      "spatial_type": "tbar",
      "spatial_payload": [
        [
          359.6517133783422,
          378.6248735838789
        ],
        [
          360.93814847755436,
          376.1689520308375
        ]
      ],
      "classification_payloads": [
        {
          "class_id": 6,
          "confidence": 1
        }
      ],
      "line_size": 1.8712706657350524,
      "containing_box": {
        "tlx": 354.03790138113703,
        "tly": 370.5551400336323,
        "brx": 366.55196047475954,
        "bry": 384.2386855810841,
        "tlz": 7,
        "brz": 7
      },
      "frame": 27,
      "text_payload": "",
      "annotation_meta": {}
    },
    {
      "id": "4f12c22b-4a02-4754-8d6c-ad56edf85639",
      "new": true,
      "parent_id": "24603c5f-b501-4676-b9ed-c19c837a024d",
      "created_by": "helle246",
      "created_at": "2021-05-28T20:02:58.458Z",
      "deprecated": false,
      "spatial_type": "tbar",
      "spatial_payload": [
        [
          321.885063217649,
          380.33328723713043
        ],
        [
          320.1799753360579,
          378.817653564605
        ]
      ],
      "classification_payloads": [
        {
          "class_id": 6,
          "confidence": 1
        }
      ],
      "line_size": 1.5157292392453923,
      "containing_box": {
        "tlx": 315.63278761832174,
        "tly": 374.27046584686883,
        "brx": 326.4322509353852,
        "bry": 384.8804749548666,
        "tlz": 6,
        "brz": 6
      },
      "frame": 26,
      "text_payload": "",
      "annotation_meta": {}
    },
    {
      "id": "5383b8a1-ede2-4d61-bd34-798d43bf8f1f",
      "new": true,
      "parent_id": "0734c2d8-3e03-4296-b5af-1f0c58512821",
      "created_by": "helle246",
      "created_at": "2021-05-28T20:02:56.864Z",
      "deprecated": false,
      "spatial_type": "tbar",
      "spatial_payload": [
        [
          319.6705218973116,
          411.91239193226875
        ],
        [
          317.8707069111876,
          413.04911718666284
        ]
      ],
      "classification_payloads": [
        {
          "class_id": 6,
          "confidence": 1
        }
      ],
      "line_size": 1.5157292392453923,
      "containing_box": {
        "tlx": 313.32351919345143,
        "tly": 407.3652042145326,
        "brx": 324.21770961504774,
        "bry": 417.596304904399,
        "tlz": 6,
        "brz": 6
      },
      "frame": 26,
      "text_payload": "",
      "annotation_meta": {}
    },
    {
      "id": "e9b32378-e6d0-4eba-92fa-aa7de0a5734e",
      "new": true,
      "parent_id": "7ecdf1a6-d98b-449e-aeec-f107dacafabd",
      "created_by": "helle246",
      "created_at": "2021-05-28T20:04:01.803Z",
      "deprecated": false,
      "spatial_type": "tbar",
      "spatial_payload": [
        [
          374.0052829502864,
          413.0564642150467
        ],
        [
          376.1103585671791,
          413.87510473272715
        ]
      ],
      "classification_payloads": [
        {
          "class_id": 6,
          "confidence": 1
        }
      ],
      "line_size": 1.8712706657350524,
      "containing_box": {
        "tlx": 368.39147095308124,
        "tly": 407.4426522178415,
        "brx": 381.7241705643843,
        "bry": 419.4889167299323,
        "tlz": 7,
        "brz": 7
      },
      "frame": 27,
      "text_payload": "",
      "annotation_meta": {}
    },
    {
      "id": "fb4c3899-411c-4bf3-89f1-daa6da807a23",
      "new": true,
      "parent_id": "a7eb62af-b8be-4a03-ac79-d17bd72eac51",
      "created_by": "helle246",
      "created_at": "2021-05-28T20:03:47.281Z",
      "deprecated": false,
      "spatial_type": "tbar",
      "spatial_payload": [
        [
          335.09097862201816,
          372.5274881714446
        ],
        [
          334.5062353951035,
          370.65630984531776
        ]
      ],
      "classification_payloads": [
        {
          "class_id": 6,
          "confidence": 1
        }
      ],
      "line_size": 1.8712706657350524,
      "containing_box": {
        "tlx": 328.8924233978983,
        "tly": 365.0424978481126,
        "brx": 340.70479061922333,
        "bry": 378.14130016864976,
        "tlz": 5,
        "brz": 5
      },
      "frame": 25,
      "text_payload": "",
      "annotation_meta": {}
    },
    {
      "id": "f995befd-0121-4956-ba86-118a5ed9ca5c",
      "new": true,
      "parent_id": null,
      "created_by": "helle246",
      "created_at": "2021-06-17T01:35:38.527Z",
      "deprecated": false,
      "spatial_type": "tbar",
      "spatial_payload": [
        [
          326.4573134328358,
          381.47820895522386
        ],
        [
          324.2157213930348,
          380.15363184079604
        ]
      ],
      "classification_payloads": [
        {
          "class_id": 6,
          "confidence": 1
        }
      ],
      "line_size": 1.6302510039883777,
      "containing_box": {
        "tlx": 319.32496838106965,
        "tly": 375.2628788288309,
        "brx": 331.34806644480096,
        "bry": 386.368961967189,
        "tlz": 5,
        "brz": 5
      },
      "frame": 25,
      "text_payload": "",
      "annotation_meta": {}
    },
    {
      "id": "ed1ae248-be39-48f8-ba1b-2753e46e041d",
      "new": true,
      "parent_id": "3468f8db-5754-431c-8f08-2d9af216dac2",
      "created_by": "helle246",
      "created_at": "2021-05-28T20:03:45.443Z",
      "deprecated": false,
      "spatial_type": "tbar",
      "spatial_payload": [
        [
          323.96228433732017,
          415.56254911543135
        ],
        [
          322.558900592725,
          416.3811896331119
        ]
      ],
      "classification_payloads": [
        {
          "class_id": 6,
          "confidence": 1
        }
      ],
      "line_size": 1.8712706657350524,
      "containing_box": {
        "tlx": 316.94508859551985,
        "tly": 409.9487371182262,
        "brx": 329.57609633452535,
        "bry": 421.99500163031706,
        "tlz": 5,
        "brz": 5
      },
      "frame": 25,
      "text_payload": "",
      "annotation_meta": {}
    },
    {
      "id": "41421635-4af3-4f59-8fdb-2ff6dc86cd15",
      "new": true,
      "parent_id": null,
      "created_by": "helle246",
      "created_at": "2021-06-17T01:35:41.909Z",
      "deprecated": false,
      "spatial_type": "tbar",
      "spatial_payload": [
        [
          320.4457711442786,
          396.150447761194
        ],
        [
          318.71363184079604,
          396.04855721393034
        ]
      ],
      "classification_payloads": [
        {
          "class_id": 6,
          "confidence": 1
        }
      ],
      "line_size": 1.6302510039883777,
      "containing_box": {
        "tlx": 313.8228788288309,
        "tly": 391.1578042019652,
        "brx": 325.33652415624374,
        "bry": 401.0412007731592,
        "tlz": 5,
        "brz": 5
      },
      "frame": 25,
      "text_payload": "",
      "annotation_meta": {}
    },
    {
      "id": "77d6a7f3-c6e0-4aa0-b9c7-ce672ef5fe9b",
      "new": true,
      "parent_id": "b6e13899-cc5f-41c3-acc8-4df0689ad7cb",
      "created_by": "helle246",
      "created_at": "2021-05-28T20:03:38.700Z",
      "deprecated": false,
      "spatial_type": "tbar",
      "spatial_payload": [
        [
          332.21343425523446,
          374.0734235661152
        ],
        [
          330.8100505106393,
          372.43614253075424
        ]
      ],
      "classification_payloads": [
        {
          "class_id": 6,
          "confidence": 1
        }
      ],
      "line_size": 1.8712706657350524,
      "containing_box": {
        "tlx": 325.19623851343414,
        "tly": 366.82233053354906,
        "brx": 337.82724625243964,
        "bry": 379.68723556332037,
        "tlz": 4,
        "brz": 4
      },
      "frame": 24,
      "text_payload": "",
      "annotation_meta": {}
    },
    {
      "id": "7c8e00bd-ba4a-4286-8dc3-e58a36c8dc33",
      "new": true,
      "parent_id": "db7abb3c-e98f-446d-bdf3-48b966ab2a58",
      "created_by": "helle246",
      "created_at": "2021-05-28T20:03:36.840Z",
      "deprecated": true,
      "spatial_type": "tbar",
      "spatial_payload": [
        [
          316.4630344062001,
          400.6368219205617
        ],
        [
          313.7732155623928,
          401.68935972900806
        ]
      ],
      "classification_payloads": [
        {
          "class_id": 6,
          "confidence": 1
        }
      ],
      "line_size": 1.8712706657350524,
      "containing_box": {
        "tlx": 308.15940356518763,
        "tly": 395.02300992335654,
        "brx": 322.0768464034053,
        "bry": 407.30317172621324,
        "tlz": 4,
        "brz": 4
      },
      "frame": 24,
      "text_payload": "",
      "annotation_meta": {}
    },
    {
      "id": "f3ee6acc-6c5d-49d3-95b8-d307295af156",
      "new": true,
      "parent_id": null,
      "created_by": "helle246",
      "created_at": "2021-06-17T01:35:49.406Z",
      "deprecated": false,
      "spatial_type": "tbar",
      "spatial_payload": [
        [
          319.22308457711443,
          393.39940298507463
        ],
        [
          317.2871641791045,
          392.4823880597015
        ]
      ],
      "classification_payloads": [
        {
          "class_id": 6,
          "confidence": 1
        }
      ],
      "line_size": 1.6302510039883777,
      "containing_box": {
        "tlx": 312.3964111671393,
        "tly": 387.59163504773636,
        "brx": 324.1138375890796,
        "bry": 398.2901559970398,
        "tlz": 4,
        "brz": 4
      },
      "frame": 24,
      "text_payload": "",
      "annotation_meta": {}
    },
    {
      "id": "fe33bc10-289a-47e2-8900-79e870133ad7",
      "new": true,
      "parent_id": null,
      "created_by": "helle246",
      "created_at": "2021-06-17T01:35:50.543Z",
      "deprecated": false,
      "spatial_type": "tbar",
      "spatial_payload": [
        [
          320.3438805970149,
          413.3699502487562
        ],
        [
          318.5098507462687,
          414.38885572139304
        ]
      ],
      "classification_payloads": [
        {
          "class_id": 6,
          "confidence": 1
        }
      ],
      "line_size": 1.6302510039883777,
      "containing_box": {
        "tlx": 313.6190977343035,
        "tly": 408.47919723679104,
        "brx": 325.23463360898006,
        "bry": 419.2796087333582,
        "tlz": 4,
        "brz": 4
      },
      "frame": 24,
      "text_payload": "",
      "annotation_meta": {}
    },
    {
      "id": "ea5cf0d9-844a-4cee-a5cb-e77086f4902e",
      "new": true,
      "parent_id": "778e34e9-d526-49b5-99b1-36d3a60242f6",
      "created_by": "helle246",
      "created_at": "2021-05-28T20:06:49.366Z",
      "deprecated": true,
      "spatial_type": "tbar",
      "spatial_payload": [
        [
          313.1884723354782,
          386.01824124769587
        ],
        [
          312.0189858816489,
          385.43349802078126
        ]
      ],
      "classification_payloads": [
        {
          "class_id": 6,
          "confidence": 1
        }
      ],
      "line_size": 1.8712706657350524,
      "containing_box": {
        "tlx": 306.40517388444374,
        "tly": 379.8196860235761,
        "brx": 318.80228433268337,
        "bry": 391.63205324490104,
        "tlz": 3,
        "brz": 3
      },
      "frame": 23,
      "text_payload": "",
      "annotation_meta": {}
    },
    {
      "id": "911c25e6-b36c-40df-86c3-b5c1a6f9436e",
      "new": true,
      "parent_id": null,
      "created_by": "helle246",
      "created_at": "2021-06-17T01:35:54.759Z",
      "deprecated": false,
      "spatial_type": "tbar",
      "spatial_payload": [
        [
          323.196815920398,
          395.1315422885572
        ],
        [
          320.95522388059703,
          395.02965174129355
        ]
      ],
      "classification_payloads": [
        {
          "class_id": 6,
          "confidence": 1
        }
      ],
      "line_size": 1.6302510039883777,
      "containing_box": {
        "tlx": 316.0644708686319,
        "tly": 390.1388987293284,
        "brx": 328.0875689323632,
        "bry": 400.0222953005224,
        "tlz": 3,
        "brz": 3
      },
      "frame": 23,
      "text_payload": "",
      "annotation_meta": {}
    },
    {
      "id": "dead039f-f182-40b0-923a-f5faef440bcc",
      "new": true,
      "parent_id": "7cb86cca-705f-4d76-937b-d8570fc4669a",
      "created_by": "helle246",
      "created_at": "2021-05-28T20:06:40.832Z",
      "deprecated": false,
      "spatial_type": "tbar",
      "spatial_payload": [
        [
          325.63120051385783,
          413.60406149532145
        ],
        [
          324.11086812387975,
          414.305753367619
        ]
      ],
      "classification_payloads": [
        {
          "class_id": 6,
          "confidence": 1
        }
      ],
      "line_size": 1.8712706657350524,
      "containing_box": {
        "tlx": 318.4970561266746,
        "tly": 407.99024949811627,
        "brx": 331.245012511063,
        "bry": 419.91956536482417,
        "tlz": 3,
        "brz": 3
      },
      "frame": 23,
      "text_payload": "",
      "annotation_meta": {}
    },
    {
      "id": "198f1e45-8263-4d5d-a17f-a925a35d67a4",
      "new": true,
      "parent_id": "cae53ec5-42b1-4ef9-aad6-e81d19da851f",
      "created_by": "helle246",
      "created_at": "2021-05-28T20:06:51.783Z",
      "deprecated": false,
      "spatial_type": "tbar",
      "spatial_payload": [
        [
          334.52281257864655,
          375.3538265288433
        ],
        [
          334.4058639332636,
          373.2487509119506
        ]
      ],
      "classification_payloads": [
        {
          "class_id": 6,
          "confidence": 1
        }
      ],
      "line_size": 1.8712706657350524,
      "containing_box": {
        "tlx": 328.79205193605844,
        "tly": 367.6349389147454,
        "brx": 340.1366245758517,
        "bry": 380.96763852604846,
        "tlz": 3,
        "brz": 3
      },
      "frame": 23,
      "text_payload": "",
      "annotation_meta": {}
    },
    {
      "id": "49ac2be8-597d-40d9-9cc6-efb8f94f8d1f",
      "new": true,
      "parent_id": "155e2063-d0ae-4946-bc41-c68dd0cdfb92",
      "created_by": "helle246",
      "created_at": "2021-05-28T20:07:54.954Z",
      "deprecated": true,
      "spatial_type": "tbar",
      "spatial_payload": [
        [
          317.2816749238806,
          406.601202835091
        ],
        [
          316.3460857608172,
          408.12153522506907
        ]
      ],
      "classification_payloads": [
        {
          "class_id": 6,
          "confidence": 1
        }
      ],
      "line_size": 1.8712706657350524,
      "containing_box": {
        "tlx": 310.732273763612,
        "tly": 400.9873908378858,
        "brx": 322.89548692108576,
        "bry": 413.73534722227424,
        "tlz": 2,
        "brz": 2
      },
      "frame": 22,
      "text_payload": "",
      "annotation_meta": {}
    },
    {
      "id": "3a80c6f6-b6c1-405b-bc56-b4b161180858",
      "new": true,
      "parent_id": "5688449c-ab58-477a-b1c4-b66da2822470",
      "created_by": "helle246",
      "created_at": "2021-05-28T20:07:42.077Z",
      "deprecated": true,
      "spatial_type": "tbar",
      "spatial_payload": [
        [
          308.74439495479936,
          389.40971156522215
        ],
        [
          307.57490850097014,
          388.82496833830754
        ]
      ],
      "classification_payloads": [
        {
          "class_id": 6,
          "confidence": 1
        }
      ],
      "line_size": 1.8712706657350524,
      "containing_box": {
        "tlx": 301.96109650376496,
        "tly": 383.21115634110237,
        "brx": 314.35820695200454,
        "bry": 395.02352356242733,
        "tlz": 2,
        "brz": 2
      },
      "frame": 22,
      "text_payload": "",
      "annotation_meta": {}
    },
    {
      "id": "d0d173a0-4924-43ef-9e8b-f4729fbee315",
      "new": true,
      "parent_id": "2abc19d6-3396-4e13-af5c-fc10ab9ae846",
      "created_by": "helle246",
      "created_at": "2021-05-28T20:07:45.721Z",
      "deprecated": true,
      "spatial_type": "tbar",
      "spatial_payload": [
        [
          327.22236749368454,
          378.0656871918527
        ],
        [
          327.22236749368454,
          377.01314938340636
        ]
      ],
      "classification_payloads": [
        {
          "class_id": 6,
          "confidence": 1
        }
      ],
      "line_size": 1.8712706657350524,
      "containing_box": {
        "tlx": 321.60855549647937,
        "tly": 371.3993373862012,
        "brx": 332.8361794908897,
        "bry": 383.6794991890579,
        "tlz": 2,
        "brz": 2
      },
      "frame": 22,
      "text_payload": "",
      "annotation_meta": {}
    },
    {
      "id": "d6ab83f8-8ba3-412b-be33-823b8ea43383",
      "new": true,
      "parent_id": "9cdf7f17-e13b-4321-affe-0b90401040fc",
      "created_by": "helle246",
      "created_at": "2021-05-28T20:07:48.204Z",
      "deprecated": true,
      "spatial_type": "tbar",
      "spatial_payload": [
        [
          348.5069632411221,
          381.45724407776174
        ],
        [
          350.261192921866,
          379.70301439701785
        ]
      ],
      "classification_payloads": [
        {
          "class_id": 6,
          "confidence": 1
        }
      ],
      "line_size": 1.8712706657350524,
      "containing_box": {
        "tlx": 342.8931512439169,
        "tly": 374.0892023998127,
        "brx": 355.87500491907116,
        "bry": 387.0710560749669,
        "tlz": 2,
        "brz": 2
      },
      "frame": 22,
      "text_payload": "",
      "annotation_meta": {}
    },
    {
      "id": "25f4a3a7-1c23-47bd-bab0-e7b6fec8e92c",
      "new": true,
      "parent_id": null,
      "created_by": "helle246",
      "created_at": "2021-06-17T01:36:03.072Z",
      "deprecated": false,
      "spatial_type": "tbar",
      "spatial_payload": [
        [
          324.5213900846284,
          406.95084492823077
        ],
        [
          322.17790749756375,
          408.07164094813123
        ]
      ],
      "classification_payloads": [
        {
          "class_id": 6,
          "confidence": 1
        }
      ],
      "line_size": 1.6302510039883777,
      "containing_box": {
        "tlx": 317.2871544855986,
        "tly": 402.0600919162656,
        "brx": 329.4121430965936,
        "bry": 412.9623939600964,
        "tlz": 2,
        "brz": 2
      },
      "frame": 22,
      "text_payload": "",
      "annotation_meta": {}
    },
    {
      "id": "22b7c175-273f-4c51-ae23-0ea0d557b4f3",
      "new": true,
      "parent_id": null,
      "created_by": "helle246",
      "created_at": "2021-06-17T01:36:04.607Z",
      "deprecated": false,
      "spatial_type": "tbar",
      "spatial_payload": [
        [
          328.3932320045331,
          388.5086544686484
        ],
        [
          326.6610927010505,
          386.77651516516585
        ]
      ],
      "classification_payloads": [
        {
          "class_id": 6,
          "confidence": 1
        }
      ],
      "line_size": 1.6302510039883777,
      "containing_box": {
        "tlx": 321.77033968908535,
        "tly": 381.8857621532007,
        "brx": 333.28398501649826,
        "bry": 393.39940748061355,
        "tlz": 2,
        "brz": 2
      },
      "frame": 22,
      "text_payload": "",
      "annotation_meta": {}
    },
    {
      "id": "21913c62-7ee3-48ed-a5c7-116fd4b49253",
      "new": true,
      "parent_id": null,
      "created_by": "helle246",
      "created_at": "2021-06-17T01:36:06.231Z",
      "deprecated": false,
      "spatial_type": "tbar",
      "spatial_payload": [
        [
          341.7408955223881,
          382.4971144278607
        ],
        [
          341.63900497512435,
          380.7649751243781
        ]
      ],
      "classification_payloads": [
        {
          "class_id": 6,
          "confidence": 1
        }
      ],
      "line_size": 1.6302510039883777,
      "containing_box": {
        "tlx": 336.7482519631592,
        "tly": 375.87422211241295,
        "brx": 346.63164853435325,
        "bry": 387.38786743982587,
        "tlz": 2,
        "brz": 2
      },
      "frame": 22,
      "text_payload": "",
      "annotation_meta": {}
    },
    {
      "id": "11679120-21f2-423e-a453-0766eb251f2e",
      "new": true,
      "parent_id": "8ff42795-723d-4046-b2f1-b4131d7bb017",
      "created_by": "helle246",
      "created_at": "2021-05-28T20:08:42.459Z",
      "deprecated": true,
      "spatial_type": "tbar",
      "spatial_payload": [
        [
          342.8934282627416,
          388.3572141553544
        ],
        [
          344.06291471657084,
          388.70806009150317
        ]
      ],
      "classification_payloads": [
        {
          "class_id": 6,
          "confidence": 1
        }
      ],
      "line_size": 1.8712706657350524,
      "containing_box": {
        "tlx": 337.27961626553645,
        "tly": 382.74340215814925,
        "brx": 349.676726713776,
        "bry": 394.32187208870835,
        "tlz": 1,
        "brz": 1
      },
      "frame": 21,
      "text_payload": "",
      "annotation_meta": {}
    },
    {
      "id": "2790c03d-6ea5-4975-bce8-0359d98968aa",
      "new": true,
      "parent_id": "244ebca0-f388-449e-80e1-d02bc395a21c",
      "created_by": "helle246",
      "created_at": "2021-05-28T20:07:15.669Z",
      "deprecated": true,
      "spatial_type": "tbar",
      "spatial_payload": [
        [
          326.28672061836596,
          377.0131955532105
        ],
        [
          326.28672061836596,
          376.0776063901471
        ]
      ],
      "classification_payloads": [
        {
          "class_id": 6,
          "confidence": 1
        }
      ],
      "line_size": 1.8712706657350524,
      "containing_box": {
        "tlx": 320.6729086211608,
        "tly": 370.4637943929419,
        "brx": 331.90053261557114,
        "bry": 382.62700755041567,
        "tlz": 1,
        "brz": 1
      },
      "frame": 21,
      "text_payload": "",
      "annotation_meta": {}
    },
    {
      "id": "a8676c44-85c3-4e32-8977-a276fdbf80a0",
      "new": true,
      "parent_id": "2c9f8c35-825b-4f30-8ff0-fd97fa50e097",
      "created_by": "helle246",
      "created_at": "2021-05-28T20:07:17.266Z",
      "deprecated": true,
      "spatial_type": "tbar",
      "spatial_payload": [
        [
          312.36983181779766,
          393.9707491337349
        ],
        [
          311.20034536396844,
          394.55549236064957
        ]
      ],
      "classification_payloads": [
        {
          "class_id": 6,
          "confidence": 1
        }
      ],
      "line_size": 1.8712706657350524,
      "containing_box": {
        "tlx": 305.58653336676326,
        "tly": 388.3569371365297,
        "brx": 317.98364381500284,
        "bry": 400.16930435785474,
        "tlz": 1,
        "brz": 1
      },
      "frame": 21,
      "text_payload": "",
      "annotation_meta": {}
    },
    {
      "id": "4835a3dc-dbc7-4fbc-a80f-bbd78db7ae8a",
      "new": true,
      "parent_id": "a4beb9f2-a83d-42da-b9c9-998b357093b5",
      "created_by": "helle246",
      "created_at": "2021-05-28T20:08:44.837Z",
      "deprecated": true,
      "spatial_type": "tbar",
      "spatial_payload": [
        [
          328.8595908167904,
          407.65374064353733
        ],
        [
          328.8595908167904,
          409.1740730335154
        ]
      ],
      "classification_payloads": [
        {
          "class_id": 6,
          "confidence": 1
        }
      ],
      "line_size": 1.8712706657350524,
      "containing_box": {
        "tlx": 323.2457788195852,
        "tly": 402.03992864633216,
        "brx": 334.47340281399556,
        "bry": 414.7878850307206,
        "tlz": 1,
        "brz": 1
      },
      "frame": 21,
      "text_payload": "",
      "annotation_meta": {}
    },
    {
      "id": "d58e3215-fa0a-427b-8650-defe9897cead",
      "new": true,
      "parent_id": null,
      "created_by": "helle246",
      "created_at": "2021-06-17T01:36:16.815Z",
      "deprecated": false,
      "spatial_type": "tbar",
      "spatial_payload": [
        [
          328.6989054726368,
          401.55064676616917
        ],
        [
          328.39323383084576,
          402.97711442786067
        ]
      ],
      "classification_payloads": [
        {
          "class_id": 6,
          "confidence": 1
        }
      ],
      "line_size": 1.6302510039883777,
      "containing_box": {
        "tlx": 323.5024808188806,
        "tly": 396.659893754204,
        "brx": 333.58965848460196,
        "bry": 407.86786743982583,
        "tlz": 1,
        "brz": 1
      },
      "frame": 21,
      "text_payload": "",
      "annotation_meta": {}
    },
    {
      "id": "78fea1ff-1e19-46ff-974e-31f6ae6fd15a",
      "new": true,
      "parent_id": null,
      "created_by": "helle246",
      "created_at": "2021-06-17T01:36:17.622Z",
      "deprecated": false,
      "spatial_type": "tbar",
      "spatial_payload": [
        [
          321.9741293532338,
          394.0107462686567
        ],
        [
          321.5665671641791,
          394.21452736318406
        ]
      ],
      "classification_payloads": [
        {
          "class_id": 6,
          "confidence": 1
        }
      ],
      "line_size": 1.6302510039883777,
      "containing_box": {
        "tlx": 316.67581415221395,
        "tly": 389.11999325669154,
        "brx": 326.864882365199,
        "bry": 399.1052803751492,
        "tlz": 1,
        "brz": 1
      },
      "frame": 21,
      "text_payload": "",
      "annotation_meta": {}
    },
    {
      "id": "4bf9cd77-a102-4b16-9217-b22f467c8453",
      "new": true,
      "parent_id": null,
      "created_by": "helle246",
      "created_at": "2021-06-17T01:36:18.487Z",
      "deprecated": false,
      "spatial_type": "tbar",
      "spatial_payload": [
        [
          326.96676616915425,
          383.0065671641791
        ],
        [
          326.3554228855721,
          381.58009950248754
        ]
      ],
      "classification_payloads": [
        {
          "class_id": 6,
          "confidence": 1
        }
      ],
      "line_size": 1.6302510039883777,
      "containing_box": {
        "tlx": 321.46466987360697,
        "tly": 376.6893464905224,
        "brx": 331.8575191811194,
        "bry": 387.89732017614426,
        "tlz": 1,
        "brz": 1
      },
      "frame": 21,
      "text_payload": "",
      "annotation_meta": {}
    },
    {
      "id": "f3da4af9-ce70-4ed8-8193-fbf419e90513",
      "new": true,
      "parent_id": null,
      "created_by": "helle246",
      "created_at": "2021-06-17T01:36:19.277Z",
      "deprecated": false,
      "spatial_type": "tbar",
      "spatial_payload": [
        [
          339.6011940298508,
          384.02547263681595
        ],
        [
          340.11064676616917,
          383.21034825870646
        ]
      ],
      "classification_payloads": [
        {
          "class_id": 6,
          "confidence": 1
        }
      ],
      "line_size": 1.6302510039883777,
      "containing_box": {
        "tlx": 334.7104410178856,
        "tly": 378.3195952467413,
        "brx": 345.0013997781343,
        "bry": 388.9162256487811,
        "tlz": 1,
        "brz": 1
      },
      "frame": 21,
      "text_payload": "",
      "annotation_meta": {}
    },
    {
      "id": "946c4fa7-6102-4431-aa7b-b2164b3eaf6b",
      "new": true,
      "parent_id": null,
      "created_by": "helle246",
      "created_at": "2021-06-17T01:36:20.061Z",
      "deprecated": false,
      "spatial_type": "tbar",
      "spatial_payload": [
        [
          341.5371144278607,
          397.0674626865672
        ],
        [
          341.63900497512435,
          397.16935323383086
        ]
      ],
      "classification_payloads": [
        {
          "class_id": 6,
          "confidence": 1
        }
      ],
      "line_size": 1.6302510039883777,
      "containing_box": {
        "tlx": 336.6463614158955,
        "tly": 392.176709674602,
        "brx": 346.5297579870895,
        "bry": 402.060106245796,
        "tlz": 1,
        "brz": 1
      },
      "frame": 21,
      "text_payload": "",
      "annotation_meta": {}
    }
  ]
}