{
  "task_meta": {},
  "annotations": [
    {
      "id": "c89ee2ba-0f4b-49a3-8d91-68d772f39314",
      "new": false,
      "parent_id": null,
      "created_by": "guest",
      "created_at": "2021-06-21T07:50:55.736Z",
      "deprecated": true,
      "spatial_type": "contour",
      "spatial_payload": [
        [
          356.17391304347825,
          286.6734074823054
        ],
        [
          356.17391304347825,
          286.6734074823054
        ],
        [
          355.26794742163804,
          286.6734074823054
        ],
        [
          354.49140546006066,
          286.6734074823054
        ],
        [
          353.71486349848334,
          286.80283114256827
        ],
        [
          352.93832153690596,
          287.06167846309404
        ],
        [
          352.16177957532864,
          287.3205257836198
        ],
        [
          351.51466127401414,
          287.7087967644085
        ],
        [
          351.25581395348837,
          288.48533872598586
        ],
        [
          351.25581395348837,
          289.2618806875632
        ],
        [
          351.51466127401414,
          290.03842264914056
        ],
        [
          351.9029322548028,
          290.685540950455
        ],
        [
          352.4206268958544,
          291.4620829120324
        ],
        [
          352.93832153690596,
          292.1092012133468
        ],
        [
          353.71486349848334,
          292.2386248736097
        ],
        [
          354.49140546006066,
          291.9797775530839
        ],
        [
          355.13852376137515,
          291.59150657229526
        ],
        [
          355.7856420626896,
          290.94438827098077
        ],
        [
          356.30333670374114,
          290.16784630940344
        ],
        [
          356.69160768452986,
          289.52072800808895
        ],
        [
          356.95045500505563,
          288.74418604651163
        ],
        [
          356.95045500505563,
          287.96764408493425
        ],
        [
          356.82103134479274,
          287.1911021233569
        ],
        [
          356.17391304347825,
          286.6734074823054
        ]
      ],
      "classification_payloads": [
        {
          "class_id": 5,
          "confidence": 1
        }
      ],
      "line_size": 0.7982996255858318,
      "containing_box": {
        "tlx": 348.86091507673086,
        "tly": 284.27850860554787,
        "brx": 359.34535388181314,
        "bry": 294.6335237503672,
        "tlz": 1,
        "brz": 1
      },
      "frame": 266,
      "text_payload": "",
      "annotation_meta": {}
    },
    {
      "id": "691ed6b3-e8c1-497f-a33b-e9fa191dae9e",
      "new": false,
      "parent_id": null,
      "created_by": "guest",
      "created_at": "2021-06-21T07:51:19.398Z",
      "deprecated": true,
      "spatial_type": "contour",
      "spatial_payload": [
        [
          356.30333670374114,
          286.5439838220425
        ],
        [
          356.30333670374114,
          286.5439838220425
        ],
        [
          355.5267947421638,
          286.5439838220425
        ],
        [
          354.75025278058644,
          286.5439838220425
        ],
        [
          353.9737108190091,
          286.80283114256827
        ],
        [
          353.3265925176946,
          287.1911021233569
        ],
        [
          352.6794742163802,
          287.5793731041456
        ],
        [
          352.03235591506575,
          287.96764408493425
        ],
        [
          351.7735085945399,
          288.74418604651163
        ],
        [
          351.51466127401414,
          289.6501516683519
        ],
        [
          351.51466127401414,
          290.4266936299292
        ],
        [
          351.7735085945399,
          291.3326592517695
        ],
        [
          352.16177957532864,
          292.1092012133468
        ],
        [
          352.8088978766431,
          292.7563195146613
        ],
        [
          353.58543983822045,
          292.8857431749242
        ],
        [
          354.3619817997978,
          293.0151668351871
        ],
        [
          355.13852376137515,
          293.0151668351871
        ],
        [
          355.7856420626896,
          292.62689585439836
        ],
        [
          356.432760364004,
          291.9797775530839
        ],
        [
          356.82103134479274,
          291.07381193124365
        ],
        [
          357.0798786653185,
          290.29726996966633
        ],
        [
          357.4681496461072,
          289.6501516683519
        ],
        [
          357.4681496461072,
          288.8736097067745
        ],
        [
          357.4681496461072,
          288.0970677451972
        ],
        [
          357.0798786653185,
          287.4499494438827
        ],
        [
          356.432760364004,
          286.93225480283115
        ],
        [
          355.7856420626896,
          286.5439838220425
        ]
      ],
      "classification_payloads": [
        {
          "class_id": 5,
          "confidence": 1
        }
      ],
      "line_size": 0.7982996255858318,
      "containing_box": {
        "tlx": 349.11976239725664,
        "tly": 284.149084945285,
        "brx": 359.8630485228647,
        "bry": 295.4100657119446,
        "tlz": 2,
        "brz": 2
      },
      "frame": 267,
      "text_payload": "",
      "annotation_meta": {}
    },
    {
      "id": "b19a38e3-52f1-4b28-9827-4d869e1cf924",
      "new": false,
      "parent_id": null,
      "created_by": "guest",
      "created_at": "2021-06-21T07:51:31.877Z",
      "deprecated": true,
      "spatial_type": "contour",
      "spatial_payload": [
        [
          353.9737108190091,
          292.62689585439836
        ],
        [
          353.9737108190091,
          292.62689585439836
        ],
        [
          353.3265925176946,
          292.2386248736097
        ],
        [
          352.6794742163802,
          291.72093023255815
        ],
        [
          352.16177957532864,
          291.07381193124365
        ],
        [
          351.7735085945399,
          290.4266936299292
        ],
        [
          351.7735085945399,
          289.6501516683519
        ],
        [
          351.7735085945399,
          288.8736097067745
        ],
        [
          352.03235591506575,
          288.0970677451972
        ],
        [
          352.6794742163802,
          287.4499494438827
        ],
        [
          353.3265925176946,
          286.93225480283115
        ],
        [
          354.103134479272,
          286.6734074823054
        ],
        [
          355.0091001011122,
          286.5439838220425
        ],
        [
          355.7856420626896,
          286.5439838220425
        ],
        [
          356.5621840242669,
          286.93225480283115
        ],
        [
          357.0798786653185,
          287.5793731041456
        ],
        [
          357.4681496461072,
          288.2264914054601
        ],
        [
          357.4681496461072,
          289.0030333670374
        ],
        [
          357.4681496461072,
          289.7795753286148
        ],
        [
          357.3387259858443,
          290.5561172901921
        ],
        [
          356.95045500505563,
          291.2032355915066
        ],
        [
          356.5621840242669,
          291.85035389282103
        ],
        [
          355.7856420626896,
          292.49747219413547
        ],
        [
          355.0091001011122,
          292.7563195146613
        ],
        [
          354.2325581395349,
          292.7563195146613
        ],
        [
          353.58543983822045,
          292.3680485338726
        ]
      ],
      "classification_payloads": [
        {
          "class_id": 5,
          "confidence": 1
        }
      ],
      "line_size": 0.7982996255858318,
      "containing_box": {
        "tlx": 349.3786097177824,
        "tly": 284.149084945285,
        "brx": 359.8630485228647,
        "bry": 295.1512183914188,
        "tlz": 3,
        "brz": 3
      },
      "frame": 268,
      "text_payload": "",
      "annotation_meta": {}
    },
    {
      "id": "034e86f5-1433-4b45-8cf8-caf1a8c7be19",
      "new": false,
      "parent_id": null,
      "created_by": "guest",
      "created_at": "2021-06-21T07:51:48.997Z",
      "deprecated": true,
      "spatial_type": "contour",
      "spatial_payload": [
        [
          353.3265925176946,
          292.1092012133468
        ],
        [
          353.3265925176946,
          292.1092012133468
        ],
        [
          352.6794742163802,
          291.72093023255815
        ],
        [
          352.16177957532864,
          291.07381193124365
        ],
        [
          352.03235591506575,
          290.29726996966633
        ],
        [
          352.03235591506575,
          289.52072800808895
        ],
        [
          352.2912032355915,
          288.74418604651163
        ],
        [
          352.6794742163802,
          288.0970677451972
        ],
        [
          353.19716885743173,
          287.4499494438827
        ],
        [
          353.8442871587462,
          287.06167846309404
        ],
        [
          354.62082912032355,
          286.93225480283115
        ],
        [
          355.3973710819009,
          286.93225480283115
        ],
        [
          356.17391304347825,
          286.93225480283115
        ],
        [
          356.95045500505563,
          286.93225480283115
        ],
        [
          357.59757330637007,
          287.3205257836198
        ],
        [
          357.9858442871587,
          287.96764408493425
        ],
        [
          358.24469160768456,
          288.74418604651163
        ],
        [
          358.24469160768456,
          289.52072800808895
        ],
        [
          358.24469160768456,
          290.29726996966633
        ],
        [
          357.9858442871587,
          291.07381193124365
        ],
        [
          357.59757330637007,
          291.72093023255815
        ],
        [
          356.95045500505563,
          292.3680485338726
        ],
        [
          356.30333670374114,
          292.7563195146613
        ],
        [
          355.5267947421638,
          292.8857431749242
        ],
        [
          354.75025278058644,
          292.8857431749242
        ],
        [
          353.9737108190091,
          292.8857431749242
        ],
        [
          353.3265925176946,
          292.49747219413547
        ],
        [
          352.93832153690596,
          291.85035389282103
        ]
      ],
      "classification_payloads": [
        {
          "class_id": 5,
          "confidence": 1
        }
      ],
      "line_size": 0.7982996255858318,
      "containing_box": {
        "tlx": 349.63745703830824,
        "tly": 284.53735592607364,
        "brx": 360.63959048444207,
        "bry": 295.2806420516817
      },
      "frame": 269,
      "text_payload": "",
      "annotation_meta": {}
    },
    {
      "id": "3ab48afe-295d-48e6-8ead-b9ff0c10ca22",
      "new": false,
      "parent_id": "034e86f5-1433-4b45-8cf8-caf1a8c7be19",
      "created_by": "rafat_solaiman",
      "created_at": "2021-06-21T07:51:48.997Z",
      "deprecated": true,
      "spatial_type": "contour",
      "spatial_payload": [
        [
          353.3265925176946,
          292.1092012133468
        ],
        [
          353.3265925176946,
          292.1092012133468
        ],
        [
          352.6794742163802,
          291.72093023255815
        ],
        [
          352.16177957532864,
          291.07381193124365
        ],
        [
          352.03235591506575,
          290.29726996966633
        ],
        [
          352.03235591506575,
          289.52072800808895
        ],
        [
          352.2912032355915,
          288.74418604651163
        ],
        [
          352.6794742163802,
          288.0970677451972
        ],
        [
          353.19716885743173,
          287.4499494438827
        ],
        [
          353.8442871587462,
          287.06167846309404
        ],
        [
          354.62082912032355,
          286.93225480283115
        ],
        [
          355.3973710819009,
          286.93225480283115
        ],
        [
          356.17391304347825,
          286.93225480283115
        ],
        [
          356.95045500505563,
          286.93225480283115
        ],
        [
          357.59757330637007,
          287.3205257836198
        ],
        [
          357.9858442871587,
          287.96764408493425
        ],
        [
          358.24469160768456,
          288.74418604651163
        ],
        [
          358.24469160768456,
          289.52072800808895
        ],
        [
          358.24469160768456,
          290.29726996966633
        ],
        [
          357.9858442871587,
          291.07381193124365
        ],
        [
          357.59757330637007,
          291.72093023255815
        ],
        [
          356.95045500505563,
          292.3680485338726
        ],
        [
          356.30333670374114,
          292.7563195146613
        ],
        [
          355.5267947421638,
          292.8857431749242
        ],
        [
          354.75025278058644,
          292.8857431749242
        ],
        [
          353.9737108190091,
          292.8857431749242
        ],
        [
          353.3265925176946,
          292.49747219413547
        ],
        [
          352.93832153690596,
          291.85035389282103
        ]
      ],
      "classification_payloads": [
        {
          "class_id": 5,
          "confidence": 1
        }
      ],
      "line_size": 0.7982996255858318,
      "containing_box": {
        "tlx": 349.63745703830824,
        "tly": 284.53735592607364,
        "brx": 360.63959048444207,
        "bry": 295.2806420516817
      },
      "frame": 269,
      "text_payload": "",
      "annotation_meta": {}
    },
    {
      "id": "67b70e17-556c-4e93-98a1-3b90b2f6ca35",
      "new": true,
      "parent_id": "b19a38e3-52f1-4b28-9827-4d869e1cf924",
      "created_by": "helle246",
      "created_at": "2021-06-21T07:51:31.877Z",
      "deprecated": true,
      "spatial_type": "contour",
      "spatial_payload": [
        [
          353.9737108190091,
          292.62689585439836
        ],
        [
          353.9737108190091,
          292.62689585439836
        ],
        [
          353.3265925176946,
          292.2386248736097
        ],
        [
          352.6794742163802,
          291.72093023255815
        ],
        [
          352.16177957532864,
          291.07381193124365
        ],
        [
          351.7735085945399,
          290.4266936299292
        ],
        [
          351.7735085945399,
          289.6501516683519
        ],
        [
          351.7735085945399,
          288.8736097067745
        ],
        [
          352.03235591506575,
          288.0970677451972
        ],
        [
          352.6794742163802,
          287.4499494438827
        ],
        [
          353.3265925176946,
          286.93225480283115
        ],
        [
          354.103134479272,
          286.6734074823054
        ],
        [
          355.0091001011122,
          286.5439838220425
        ],
        [
          355.7856420626896,
          286.5439838220425
        ],
        [
          356.5621840242669,
          286.93225480283115
        ],
        [
          357.0798786653185,
          287.5793731041456
        ],
        [
          357.4681496461072,
          288.2264914054601
        ],
        [
          357.4681496461072,
          289.0030333670374
        ],
        [
          357.4681496461072,
          289.7795753286148
        ],
        [
          357.3387259858443,
          290.5561172901921
        ],
        [
          356.95045500505563,
          291.2032355915066
        ],
        [
          356.5621840242669,
          291.85035389282103
        ],
        [
          355.7856420626896,
          292.49747219413547
        ],
        [
          355.0091001011122,
          292.7563195146613
        ],
        [
          354.2325581395349,
          292.7563195146613
        ],
        [
          353.58543983822045,
          292.3680485338726
        ]
      ],
      "classification_payloads": [
        {
          "class_id": 5,
          "confidence": 1
        }
      ],
      "line_size": 0.7982996255858318,
      "containing_box": {
        "tlx": 349.3786097177824,
        "tly": 284.149084945285,
        "brx": 359.8630485228647,
        "bry": 295.1512183914188,
        "tlz": 3,
        "brz": 3
      },
      "frame": 268,
      "text_payload": "",
      "annotation_meta": {}
    },
    {
      "id": "1d71a04c-a2d0-4c5e-9f25-f71c72535db1",
      "new": true,
      "parent_id": "691ed6b3-e8c1-497f-a33b-e9fa191dae9e",
      "created_by": "helle246",
      "created_at": "2021-06-21T07:51:19.398Z",
      "deprecated": true,
      "spatial_type": "contour",
      "spatial_payload": [
        [
          356.30333670374114,
          286.5439838220425
        ],
        [
          356.30333670374114,
          286.5439838220425
        ],
        [
          355.5267947421638,
          286.5439838220425
        ],
        [
          354.75025278058644,
          286.5439838220425
        ],
        [
          353.9737108190091,
          286.80283114256827
        ],
        [
          353.3265925176946,
          287.1911021233569
        ],
        [
          352.6794742163802,
          287.5793731041456
        ],
        [
          352.03235591506575,
          287.96764408493425
        ],
        [
          351.7735085945399,
          288.74418604651163
        ],
        [
          351.51466127401414,
          289.6501516683519
        ],
        [
          351.51466127401414,
          290.4266936299292
        ],
        [
          351.7735085945399,
          291.3326592517695
        ],
        [
          352.16177957532864,
          292.1092012133468
        ],
        [
          352.8088978766431,
          292.7563195146613
        ],
        [
          353.58543983822045,
          292.8857431749242
        ],
        [
          354.3619817997978,
          293.0151668351871
        ],
        [
          355.13852376137515,
          293.0151668351871
        ],
        [
          355.7856420626896,
          292.62689585439836
        ],
        [
          356.432760364004,
          291.9797775530839
        ],
        [
          356.82103134479274,
          291.07381193124365
        ],
        [
          357.0798786653185,
          290.29726996966633
        ],
        [
          357.4681496461072,
          289.6501516683519
        ],
        [
          357.4681496461072,
          288.8736097067745
        ],
        [
          357.4681496461072,
          288.0970677451972
        ],
        [
          357.0798786653185,
          287.4499494438827
        ],
        [
          356.432760364004,
          286.93225480283115
        ],
        [
          355.7856420626896,
          286.5439838220425
        ]
      ],
      "classification_payloads": [
        {
          "class_id": 5,
          "confidence": 1
        }
      ],
      "line_size": 0.7982996255858318,
      "containing_box": {
        "tlx": 349.11976239725664,
        "tly": 284.149084945285,
        "brx": 359.8630485228647,
        "bry": 295.4100657119446,
        "tlz": 2,
        "brz": 2
      },
      "frame": 267,
      "text_payload": "",
      "annotation_meta": {}
    },
    {
      "id": "d59c7615-1ec6-430f-ac54-9aebff99a406",
      "new": true,
      "parent_id": "c89ee2ba-0f4b-49a3-8d91-68d772f39314",
      "created_by": "helle246",
      "created_at": "2021-06-21T07:50:55.736Z",
      "deprecated": true,
      "spatial_type": "contour",
      "spatial_payload": [
        [
          356.17391304347825,
          286.6734074823054
        ],
        [
          356.17391304347825,
          286.6734074823054
        ],
        [
          355.26794742163804,
          286.6734074823054
        ],
        [
          354.49140546006066,
          286.6734074823054
        ],
        [
          353.71486349848334,
          286.80283114256827
        ],
        [
          352.93832153690596,
          287.06167846309404
        ],
        [
          352.16177957532864,
          287.3205257836198
        ],
        [
          351.51466127401414,
          287.7087967644085
        ],
        [
          351.25581395348837,
          288.48533872598586
        ],
        [
          351.25581395348837,
          289.2618806875632
        ],
        [
          351.51466127401414,
          290.03842264914056
        ],
        [
          351.9029322548028,
          290.685540950455
        ],
        [
          352.4206268958544,
          291.4620829120324
        ],
        [
          352.93832153690596,
          292.1092012133468
        ],
        [
          353.71486349848334,
          292.2386248736097
        ],
        [
          354.49140546006066,
          291.9797775530839
        ],
        [
          355.13852376137515,
          291.59150657229526
        ],
        [
          355.7856420626896,
          290.94438827098077
        ],
        [
          356.30333670374114,
          290.16784630940344
        ],
        [
          356.69160768452986,
          289.52072800808895
        ],
        [
          356.95045500505563,
          288.74418604651163
        ],
        [
          356.95045500505563,
          287.96764408493425
        ],
        [
          356.82103134479274,
          287.1911021233569
        ],
        [
          356.17391304347825,
          286.6734074823054
        ]
      ],
      "classification_payloads": [
        {
          "class_id": 5,
          "confidence": 1
        }
      ],
      "line_size": 0.7982996255858318,
      "containing_box": {
        "tlx": 348.86091507673086,
        "tly": 284.27850860554787,
        "brx": 359.34535388181314,
        "bry": 294.6335237503672,
        "tlz": 1,
        "brz": 1
      },
      "frame": 266,
      "text_payload": "",
      "annotation_meta": {}
    },
    {
      "id": "d1c93892-77d7-45a3-bcba-2f52af151aaf",
      "new": true,
      "parent_id": null,
      "created_by": "helle246",
      "created_at": "2021-06-29T23:01:23.180Z",
      "deprecated": false,
      "spatial_type": "contour",
      "spatial_payload": [
        [
          353.52528805336567,
          287.5459066100667
        ],
        [
          353.52528805336567,
          287.5459066100667
        ],
        [
          352.7490600363857,
          287.7942995755003
        ],
        [
          352.4385688295937,
          288.4773802304427
        ],
        [
          352.2212249848393,
          289.2846573681019
        ],
        [
          352.0970285021225,
          290.02983626440266
        ],
        [
          352.1591267434809,
          290.86816252274104
        ],
        [
          352.8732565191025,
          291.30285021224984
        ],
        [
          353.64948453608247,
          291.33389933292904
        ],
        [
          354.42571255306245,
          291.33389933292904
        ],
        [
          355.07774408732564,
          290.96130988477864
        ],
        [
          355.38823529411764,
          290.18508186779866
        ],
        [
          355.45033353547603,
          289.4088538508187
        ],
        [
          355.17089144936324,
          288.6326258338387
        ],
        [
          354.70515463917525,
          288.0426925409339
        ],
        [
          353.99102486355366,
          287.7011522134627
        ],
        [
          353.1526986052153,
          287.5769557307459
        ]
      ],
      "classification_payloads": [
        {
          "class_id": 5,
          "confidence": 1
        }
      ],
      "line_size": 0.4967739433356471,
      "containing_box": {
        "tlx": 352.0970285021225,
        "tly": 287.5459066100667,
        "brx": 355.45033353547603,
        "bry": 291.33389933292904,
        "tlz": 1,
        "brz": 1
      },
      "frame": 266,
      "text_payload": "",
      "annotation_meta": {}
    },
    {
      "id": "5979b6ce-9f9f-4ce3-b61b-d019ffeef75e",
      "new": true,
      "parent_id": null,
      "created_by": "helle246",
      "created_at": "2021-06-29T23:01:27.979Z",
      "deprecated": false,
      "spatial_type": "contour",
      "spatial_payload": [
        [
          354.11522134627046,
          287.2975136446331
        ],
        [
          354.11522134627046,
          287.2975136446331
        ],
        [
          353.3700424499697,
          287.5459066100667
        ],
        [
          352.7490600363857,
          287.9805942995755
        ],
        [
          352.3764705882353,
          288.6326258338387
        ],
        [
          352.1901758641601,
          289.4088538508187
        ],
        [
          352.1901758641601,
          290.24718010915706
        ],
        [
          352.5627653123105,
          290.93026076409944
        ],
        [
          353.3389933292905,
          291.27180109157064
        ],
        [
          354.08417222559126,
          291.42704669496663
        ],
        [
          355.01564584596724,
          291.36494845360824
        ],
        [
          355.69872650090963,
          290.93026076409944
        ],
        [
          356.1023650697392,
          290.21613098847786
        ],
        [
          356.1955124317768,
          289.4399029714979
        ],
        [
          355.8539721043056,
          288.6636749545179
        ],
        [
          355.26403881140084,
          288.0426925409339
        ],
        [
          354.54990903577925,
          287.5769557307459
        ],
        [
          353.77368101879927,
          287.4217101273499
        ]
      ],
      "classification_payloads": [
        {
          "class_id": 5,
          "confidence": 1
        }
      ],
      "line_size": 0.4967739433356471,
      "containing_box": {
        "tlx": 352.1901758641601,
        "tly": 287.2975136446331,
        "brx": 356.1955124317768,
        "bry": 291.42704669496663,
        "tlz": 2,
        "brz": 2
      },
      "frame": 267,
      "text_payload": "",
      "annotation_meta": {}
    },
    {
      "id": "76b39a79-72b7-48ea-9091-ab08d0ae3165",
      "new": true,
      "parent_id": null,
      "created_by": "helle246",
      "created_at": "2021-06-29T23:01:31.660Z",
      "deprecated": false,
      "spatial_type": "contour",
      "spatial_payload": [
        [
          354.30151607034566,
          287.7011522134627
        ],
        [
          354.30151607034566,
          287.7011522134627
        ],
        [
          353.4631898120073,
          287.7322013341419
        ],
        [
          352.7490600363857,
          288.2289872650091
        ],
        [
          352.4385688295937,
          288.9741661613099
        ],
        [
          352.4385688295937,
          289.78144329896907
        ],
        [
          352.5627653123105,
          290.55767131594905
        ],
        [
          353.0906003638569,
          291.14760460885384
        ],
        [
          353.83577926015766,
          291.42704669496663
        ],
        [
          354.61200727713765,
          291.45809581564583
        ],
        [
          355.38823529411764,
          291.33389933292904
        ],
        [
          355.9471194663432,
          290.74396604002425
        ],
        [
          356.226561552456,
          289.96773802304426
        ],
        [
          356.1644633110976,
          289.1915100060643
        ],
        [
          355.760824742268,
          288.5394784718011
        ],
        [
          355.13984232868404,
          288.0737416616131
        ],
        [
          354.39466343238325,
          287.8874469375379
        ]
      ],
      "classification_payloads": [
        {
          "class_id": 5,
          "confidence": 1
        }
      ],
      "line_size": 0.4967739433356471,
      "containing_box": {
        "tlx": 352.4385688295937,
        "tly": 287.7011522134627,
        "brx": 356.226561552456,
        "bry": 291.45809581564583,
        "tlz": 3,
        "brz": 3
      },
      "frame": 268,
      "text_payload": "",
      "annotation_meta": {}
    }
  ]
}