{
  "task_meta": {},
  "annotations": [
    {
      "id": "e6fa5bbf-b376-416e-902b-574da953c540",
      "new": false,
      "parent_id": null,
      "created_by": "rafat_solaiman",
      "created_at": "2021-06-02T02:13:39.545Z",
      "deprecated": true,
      "spatial_type": "tbar",
      "spatial_payload": [
        [
          104.79751234680812,
          348.38851289555515
        ],
        [
          104.79751234680812,
          348.66947137369675
        ]
      ],
      "classification_payloads": [
        {
          "class_id": 5,
          "confidence": 1
        }
      ],
      "line_size": 0.5251948400539858,
      "containing_box": {
        "tlx": 103.22192782664617,
        "tly": 346.8129283753932,
        "brx": 106.37309686697007,
        "bry": 350.2450558938587,
        "tlz": 3,
        "brz": 3
      },
      "frame": 25,
      "text_payload": "",
      "annotation_meta": {}
    },
    {
      "id": "72e3a32f-6201-43fa-8722-5a42e284098d",
      "new": false,
      "parent_id": null,
      "created_by": "rafat_solaiman",
      "created_at": "2021-06-02T02:13:41.097Z",
      "deprecated": true,
      "spatial_type": "tbar",
      "spatial_payload": [
        [
          101.80062191329797,
          345.1106639839034
        ],
        [
          101.70696908725078,
          345.01701115785625
        ]
      ],
      "classification_payloads": [
        {
          "class_id": 5,
          "confidence": 1
        }
      ],
      "line_size": 0.5251948400539858,
      "containing_box": {
        "tlx": 100.13138456708883,
        "tly": 343.4414266376943,
        "brx": 103.37620643345993,
        "bry": 346.68624850406536,
        "tlz": 3,
        "brz": 3
      },
      "frame": 25,
      "text_payload": "",
      "annotation_meta": {}
    },
    {
      "id": "6f8f250c-cf24-4614-8914-f5083a062f25",
      "new": false,
      "parent_id": null,
      "created_by": "rafat_solaiman",
      "created_at": "2021-06-02T02:13:42.404Z",
      "deprecated": true,
      "spatial_type": "tbar",
      "spatial_payload": [
        [
          107.23248582403512,
          342.488384854582
        ],
        [
          107.23248582403512,
          342.11377355039326
        ]
      ],
      "classification_payloads": [
        {
          "class_id": 5,
          "confidence": 1
        }
      ],
      "line_size": 0.5251948400539858,
      "containing_box": {
        "tlx": 105.65690130387317,
        "tly": 340.5381890302313,
        "brx": 108.80807034419708,
        "bry": 344.063969374744,
        "tlz": 3,
        "brz": 3
      },
      "frame": 25,
      "text_payload": "",
      "annotation_meta": {}
    },
    {
      "id": "72af2c11-de86-49a8-a7d1-c8ba490f8514",
      "new": false,
      "parent_id": null,
      "created_by": "rafat_solaiman",
      "created_at": "2021-06-02T02:13:44.188Z",
      "deprecated": true,
      "spatial_type": "tbar",
      "spatial_payload": [
        [
          101.61331626120358,
          348.0139015913664
        ],
        [
          101.51966343515639,
          348.10755441741355
        ]
      ],
      "classification_payloads": [
        {
          "class_id": 5,
          "confidence": 1
        }
      ],
      "line_size": 0.5251948400539858,
      "containing_box": {
        "tlx": 99.94407891499444,
        "tly": 346.43831707120444,
        "brx": 103.18890078136553,
        "bry": 349.6831389375755,
        "tlz": 3,
        "brz": 3
      },
      "frame": 25,
      "text_payload": "",
      "annotation_meta": {}
    },
    {
      "id": "37c362c8-baaa-429f-993c-fc26be04f54f",
      "new": false,
      "parent_id": null,
      "created_by": "rafat_solaiman",
      "created_at": "2021-06-02T02:13:45.673Z",
      "deprecated": true,
      "spatial_type": "tbar",
      "spatial_payload": [
        [
          109.29284799707335,
          349.60599963416865
        ],
        [
          109.29284799707335,
          349.79330528626303
        ]
      ],
      "classification_payloads": [
        {
          "class_id": 5,
          "confidence": 1
        }
      ],
      "line_size": 0.5251948400539858,
      "containing_box": {
        "tlx": 107.7172634769114,
        "tly": 348.0304151140067,
        "brx": 110.8684325172353,
        "bry": 351.368889806425,
        "tlz": 3,
        "brz": 3
      },
      "frame": 25,
      "text_payload": "",
      "annotation_meta": {}
    },
    {
      "id": "d1183a59-2df6-44b4-9f0e-49cc61712b38",
      "new": false,
      "parent_id": null,
      "created_by": "rafat_solaiman",
      "created_at": "2021-06-02T02:13:47.204Z",
      "deprecated": true,
      "spatial_type": "tbar",
      "spatial_payload": [
        [
          114.91201755990488,
          347.26467898298887
        ],
        [
          115.00567038595207,
          347.45198463508325
        ]
      ],
      "classification_payloads": [
        {
          "class_id": 5,
          "confidence": 1
        }
      ],
      "line_size": 0.5251948400539858,
      "containing_box": {
        "tlx": 113.33643303974293,
        "tly": 345.6890944628269,
        "brx": 116.58125490611403,
        "bry": 349.0275691552452,
        "tlz": 3,
        "brz": 3
      },
      "frame": 25,
      "text_payload": "",
      "annotation_meta": {}
    },
    {
      "id": "f005447c-ce50-497b-902e-03148f8816ef",
      "new": false,
      "parent_id": null,
      "created_by": "rafat_solaiman",
      "created_at": "2021-06-02T02:13:49.103Z",
      "deprecated": true,
      "spatial_type": "tbar",
      "spatial_payload": [
        [
          111.82147430034755,
          342.11377355039326
        ],
        [
          111.72782147430034,
          341.9264678982989
        ]
      ],
      "classification_payloads": [
        {
          "class_id": 5,
          "confidence": 1
        }
      ],
      "line_size": 0.5251948400539858,
      "containing_box": {
        "tlx": 110.15223695413839,
        "tly": 340.3508833781369,
        "brx": 113.3970588205095,
        "bry": 343.6893580705552,
        "tlz": 3,
        "brz": 3
      },
      "frame": 25,
      "text_payload": "",
      "annotation_meta": {}
    },
    {
      "id": "b42d9ef8-bd31-4646-8bba-013852744d54",
      "new": false,
      "parent_id": null,
      "created_by": "rafat_solaiman",
      "created_at": "2021-06-02T02:13:50.308Z",
      "deprecated": true,
      "spatial_type": "tbar",
      "spatial_payload": [
        [
          115.942198646424,
          341.8328150722517
        ],
        [
          116.0358514724712,
          341.6455094201573
        ]
      ],
      "classification_payloads": [
        {
          "class_id": 5,
          "confidence": 1
        }
      ],
      "line_size": 0.5251948400539858,
      "containing_box": {
        "tlx": 114.36661412626205,
        "tly": 340.0699248999953,
        "brx": 117.61143599263315,
        "bry": 343.4083995924137,
        "tlz": 3,
        "brz": 3
      },
      "frame": 25,
      "text_payload": "",
      "annotation_meta": {}
    },
    {
      "id": "57a1bb46-d093-4b5d-9b30-69f57de20862",
      "new": false,
      "parent_id": null,
      "created_by": "rafat_solaiman",
      "created_at": "2021-06-02T02:13:51.621Z",
      "deprecated": true,
      "spatial_type": "tbar",
      "spatial_payload": [
        [
          117.53429668922627,
          344.45509420157305
        ],
        [
          117.72160234132065,
          344.45509420157305
        ]
      ],
      "classification_payloads": [
        {
          "class_id": 5,
          "confidence": 1
        }
      ],
      "line_size": 0.5251948400539858,
      "containing_box": {
        "tlx": 115.95871216906431,
        "tly": 342.8795096814111,
        "brx": 119.2971868614826,
        "bry": 346.030678721735,
        "tlz": 3,
        "brz": 3
      },
      "frame": 25,
      "text_payload": "",
      "annotation_meta": {}
    },
    {
      "id": "78dc0445-f703-43dc-8a55-bc20e415f2fb",
      "new": false,
      "parent_id": null,
      "created_by": "rafat_solaiman",
      "created_at": "2021-06-02T02:13:56.826Z",
      "deprecated": true,
      "spatial_type": "tbar",
      "spatial_payload": [
        [
          108.26266691055423,
          348.10755441741355
        ],
        [
          108.26266691055423,
          348.29486006950793
        ]
      ],
      "classification_payloads": [
        {
          "class_id": 5,
          "confidence": 1
        }
      ],
      "line_size": 0.5251948400539858,
      "containing_box": {
        "tlx": 106.68708239039228,
        "tly": 346.5319698972516,
        "brx": 109.83825143071618,
        "bry": 349.8704445896699
      },
      "frame": 24,
      "text_payload": "",
      "annotation_meta": {}
    },
    {
      "id": "fcc79fa3-b064-4c8d-96a5-881b401e07b6",
      "new": false,
      "parent_id": null,
      "created_by": "rafat_solaiman",
      "created_at": "2021-06-02T02:13:58.453Z",
      "deprecated": true,
      "spatial_type": "tbar",
      "spatial_payload": [
        [
          102.26888604353393,
          347.63929028717763
        ],
        [
          102.08158039143954,
          347.9202487653192
        ]
      ],
      "classification_payloads": [
        {
          "class_id": 5,
          "confidence": 1
        }
      ],
      "line_size": 0.5251948400539858,
      "containing_box": {
        "tlx": 100.50599587127759,
        "tly": 346.0637057670157,
        "brx": 103.84447056369588,
        "bry": 349.4958332854811,
        "tlz": 2,
        "brz": 2
      },
      "frame": 24,
      "text_payload": "",
      "annotation_meta": {}
    },
    {
      "id": "26eea161-fff6-4a73-b5cf-706987dae84b",
      "new": false,
      "parent_id": null,
      "created_by": "rafat_solaiman",
      "created_at": "2021-06-02T02:13:59.489Z",
      "deprecated": true,
      "spatial_type": "tbar",
      "spatial_payload": [
        [
          103.8609840863362,
          345.2979696359978
        ],
        [
          103.76733126028901,
          345.1106639839034
        ]
      ],
      "classification_payloads": [
        {
          "class_id": 5,
          "confidence": 1
        }
      ],
      "line_size": 0.5251948400539858,
      "containing_box": {
        "tlx": 102.19174674012706,
        "tly": 343.53507946374145,
        "brx": 105.43656860649816,
        "bry": 346.87355415615974,
        "tlz": 2,
        "brz": 2
      },
      "frame": 24,
      "text_payload": "",
      "annotation_meta": {}
    },
    {
      "id": "41a3c56b-bcc5-400b-84ff-d8a758fb70b0",
      "new": false,
      "parent_id": null,
      "created_by": "rafat_solaiman",
      "created_at": "2021-06-02T02:14:01.042Z",
      "deprecated": true,
      "spatial_type": "tbar",
      "spatial_payload": [
        [
          109.38650082312054,
          342.0201207243461
        ],
        [
          109.38650082312054,
          341.9264678982989
        ]
      ],
      "classification_payloads": [
        {
          "class_id": 5,
          "confidence": 1
        }
      ],
      "line_size": 0.5251948400539858,
      "containing_box": {
        "tlx": 107.81091630295859,
        "tly": 340.3508833781369,
        "brx": 110.9620853432825,
        "bry": 343.59570524450805
      },
      "frame": 24,
      "text_payload": "",
      "annotation_meta": {}
    },
    {
      "id": "02478a46-9508-49c5-9507-5da89a15e251",
      "new": false,
      "parent_id": null,
      "created_by": "rafat_solaiman",
      "created_at": "2021-06-02T02:14:04.791Z",
      "deprecated": false,
      "spatial_type": "tbar",
      "spatial_payload": [
        [
          108.26266691055423,
          341.8328150722517
        ],
        [
          108.16901408450704,
          341.8328150722517
        ]
      ],
      "classification_payloads": [
        {
          "class_id": 5,
          "confidence": 1
        }
      ],
      "line_size": 0.5251948400539858,
      "containing_box": {
        "tlx": 106.59342956434509,
        "tly": 340.25723055208977,
        "brx": 109.83825143071618,
        "bry": 343.4083995924137,
        "tlz": 2,
        "brz": 2
      },
      "frame": 24,
      "text_payload": "",
      "annotation_meta": {}
    },
    {
      "id": "5e891a9c-c302-40ac-b972-b481b5498b05",
      "new": false,
      "parent_id": null,
      "created_by": "rafat_solaiman",
      "created_at": "2021-06-02T02:14:07.138Z",
      "deprecated": false,
      "spatial_type": "tbar",
      "spatial_payload": [
        [
          111.82147430034755,
          339.95975855130786
        ],
        [
          111.82147430034755,
          339.67880007316626
        ]
      ],
      "classification_payloads": [
        {
          "class_id": 5,
          "confidence": 1
        }
      ],
      "line_size": 0.5251948400539858,
      "containing_box": {
        "tlx": 110.24588978018559,
        "tly": 338.1032155530043,
        "brx": 113.3970588205095,
        "bry": 341.5353430714698,
        "tlz": 2,
        "brz": 2
      },
      "frame": 24,
      "text_payload": "",
      "annotation_meta": {}
    },
    {
      "id": "17e5ae58-c53d-4867-a23f-1b87c3822db2",
      "new": false,
      "parent_id": null,
      "created_by": "rafat_solaiman",
      "created_at": "2021-06-02T02:14:08.721Z",
      "deprecated": false,
      "spatial_type": "tbar",
      "spatial_payload": [
        [
          116.22315712456557,
          340.4280226815438
        ],
        [
          116.22315712456557,
          340.14706420340224
        ]
      ],
      "classification_payloads": [
        {
          "class_id": 5,
          "confidence": 1
        }
      ],
      "line_size": 0.5251948400539858,
      "containing_box": {
        "tlx": 114.64757260440362,
        "tly": 338.5714796832403,
        "brx": 117.79874164472753,
        "bry": 342.00360720170573,
        "tlz": 2,
        "brz": 2
      },
      "frame": 24,
      "text_payload": "",
      "annotation_meta": {}
    },
    {
      "id": "c36d7dd0-ba23-4eb8-9191-f732c784ad1e",
      "new": false,
      "parent_id": null,
      "created_by": "rafat_solaiman",
      "created_at": "2021-06-02T02:14:09.899Z",
      "deprecated": true,
      "spatial_type": "tbar",
      "spatial_payload": [
        [
          118.65813060179258,
          342.39473202853486
        ],
        [
          118.93908907993415,
          342.39473202853486
        ]
      ],
      "classification_payloads": [
        {
          "class_id": 5,
          "confidence": 1
        }
      ],
      "line_size": 0.5251948400539858,
      "containing_box": {
        "tlx": 117.08254608163062,
        "tly": 340.8191475083729,
        "brx": 120.5146736000961,
        "bry": 343.9703165486968,
        "tlz": 2,
        "brz": 2
      },
      "frame": 24,
      "text_payload": "",
      "annotation_meta": {}
    },
    {
      "id": "f5e769c6-c306-49b7-b141-d02369f74a65",
      "new": false,
      "parent_id": null,
      "created_by": "rafat_solaiman",
      "created_at": "2021-06-02T02:14:11.308Z",
      "deprecated": false,
      "spatial_type": "tbar",
      "spatial_payload": [
        [
          116.59776842875435,
          346.7964148527529
        ],
        [
          116.69142125480154,
          346.98372050484727
        ]
      ],
      "classification_payloads": [
        {
          "class_id": 5,
          "confidence": 1
        }
      ],
      "line_size": 0.5251948400539858,
      "containing_box": {
        "tlx": 115.0221839085924,
        "tly": 345.22083033259094,
        "brx": 118.2670057749635,
        "bry": 348.5593050250092,
        "tlz": 2,
        "brz": 2
      },
      "frame": 24,
      "text_payload": "",
      "annotation_meta": {}
    },
    {
      "id": "57c365b1-9385-4f87-847d-7240421e46e3",
      "new": false,
      "parent_id": null,
      "created_by": "rafat_solaiman",
      "created_at": "2021-06-02T02:14:13.575Z",
      "deprecated": true,
      "spatial_type": "tbar",
      "spatial_payload": [
        [
          112.94530821291384,
          348.10755441741355
        ],
        [
          113.03896103896103,
          348.10755441741355
        ]
      ],
      "classification_payloads": [
        {
          "class_id": 5,
          "confidence": 1
        }
      ],
      "line_size": 0.5251948400539858,
      "containing_box": {
        "tlx": 111.36972369275189,
        "tly": 346.5319698972516,
        "brx": 114.61454555912299,
        "bry": 349.6831389375755
      },
      "frame": 24,
      "text_payload": "",
      "annotation_meta": {}
    },
    {
      "id": "edf439cd-f489-4704-be90-832deea6ce2e",
      "new": false,
      "parent_id": null,
      "created_by": "rafat_solaiman",
      "created_at": "2021-06-02T02:14:15.185Z",
      "deprecated": false,
      "spatial_type": "tbar",
      "spatial_payload": [
        [
          113.22626669105543,
          348.85677702579113
        ],
        [
          113.22626669105543,
          349.0440826778855
        ]
      ],
      "classification_payloads": [
        {
          "class_id": 5,
          "confidence": 1
        }
      ],
      "line_size": 0.5251948400539858,
      "containing_box": {
        "tlx": 111.65068217089348,
        "tly": 347.2811925056292,
        "brx": 114.80185121121738,
        "bry": 350.61966719804747,
        "tlz": 2,
        "brz": 2
      },
      "frame": 24,
      "text_payload": "",
      "annotation_meta": {}
    },
    {
      "id": "5064c8a8-4609-4a6e-be38-ec9020b874d3",
      "new": false,
      "parent_id": null,
      "created_by": "rafat_solaiman",
      "created_at": "2021-06-02T02:14:19.468Z",
      "deprecated": true,
      "spatial_type": "tbar",
      "spatial_payload": [
        [
          108.26266691055423,
          348.57581854764953
        ],
        [
          108.26266691055423,
          348.7631241997439
        ]
      ],
      "classification_payloads": [
        {
          "class_id": 5,
          "confidence": 1
        }
      ],
      "line_size": 0.5251948400539858,
      "containing_box": {
        "tlx": 106.68708239039228,
        "tly": 347.0002340274876,
        "brx": 109.83825143071618,
        "bry": 350.33870871990587,
        "tlz": 2,
        "brz": 2
      },
      "frame": 24,
      "text_payload": "",
      "annotation_meta": {}
    },
    {
      "id": "a7a64cdc-512a-489d-8dcc-7a8023f81635",
      "new": true,
      "parent_id": "72e3a32f-6201-43fa-8722-5a42e284098d",
      "created_by": "helle246",
      "created_at": "2021-06-02T02:13:41.097Z",
      "deprecated": true,
      "spatial_type": "tbar",
      "spatial_payload": [
        [
          101.80062191329797,
          345.1106639839034
        ],
        [
          101.70696908725078,
          345.01701115785625
        ]
      ],
      "classification_payloads": [
        {
          "class_id": 5,
          "confidence": 1
        }
      ],
      "line_size": 0.5251948400539858,
      "containing_box": {
        "tlx": 100.13138456708883,
        "tly": 343.4414266376943,
        "brx": 103.37620643345993,
        "bry": 346.68624850406536,
        "tlz": 3,
        "brz": 3
      },
      "frame": 25,
      "text_payload": "",
      "annotation_meta": {}
    },
    {
      "id": "b96669f9-081e-4e6d-9f47-4ae15b0ac1ef",
      "new": true,
      "parent_id": "e6fa5bbf-b376-416e-902b-574da953c540",
      "created_by": "helle246",
      "created_at": "2021-06-02T02:13:39.545Z",
      "deprecated": true,
      "spatial_type": "tbar",
      "spatial_payload": [
        [
          104.79751234680812,
          348.38851289555515
        ],
        [
          104.79751234680812,
          348.66947137369675
        ]
      ],
      "classification_payloads": [
        {
          "class_id": 5,
          "confidence": 1
        }
      ],
      "line_size": 0.5251948400539858,
      "containing_box": {
        "tlx": 103.22192782664617,
        "tly": 346.8129283753932,
        "brx": 106.37309686697007,
        "bry": 350.2450558938587,
        "tlz": 3,
        "brz": 3
      },
      "frame": 25,
      "text_payload": "",
      "annotation_meta": {}
    },
    {
      "id": "46cce9b4-1ae0-4078-a947-b273288200f0",
      "new": true,
      "parent_id": "72af2c11-de86-49a8-a7d1-c8ba490f8514",
      "created_by": "helle246",
      "created_at": "2021-06-02T02:13:44.188Z",
      "deprecated": true,
      "spatial_type": "tbar",
      "spatial_payload": [
        [
          101.61331626120358,
          348.0139015913664
        ],
        [
          101.51966343515639,
          348.10755441741355
        ]
      ],
      "classification_payloads": [
        {
          "class_id": 5,
          "confidence": 1
        }
      ],
      "line_size": 0.5251948400539858,
      "containing_box": {
        "tlx": 99.94407891499444,
        "tly": 346.43831707120444,
        "brx": 103.18890078136553,
        "bry": 349.6831389375755,
        "tlz": 3,
        "brz": 3
      },
      "frame": 25,
      "text_payload": "",
      "annotation_meta": {}
    },
    {
      "id": "acad5745-6dfb-46e3-a361-207e65f8433c",
      "new": true,
      "parent_id": "37c362c8-baaa-429f-993c-fc26be04f54f",
      "created_by": "helle246",
      "created_at": "2021-06-02T02:13:45.673Z",
      "deprecated": true,
      "spatial_type": "tbar",
      "spatial_payload": [
        [
          109.29284799707335,
          349.60599963416865
        ],
        [
          109.29284799707335,
          349.79330528626303
        ]
      ],
      "classification_payloads": [
        {
          "class_id": 5,
          "confidence": 1
        }
      ],
      "line_size": 0.5251948400539858,
      "containing_box": {
        "tlx": 107.7172634769114,
        "tly": 348.0304151140067,
        "brx": 110.8684325172353,
        "bry": 351.368889806425,
        "tlz": 3,
        "brz": 3
      },
      "frame": 25,
      "text_payload": "",
      "annotation_meta": {}
    },
    {
      "id": "8a795d64-82c8-48d5-894f-022a27443def",
      "new": true,
      "parent_id": "d1183a59-2df6-44b4-9f0e-49cc61712b38",
      "created_by": "helle246",
      "created_at": "2021-06-02T02:13:47.204Z",
      "deprecated": true,
      "spatial_type": "tbar",
      "spatial_payload": [
        [
          114.91201755990488,
          347.26467898298887
        ],
        [
          115.00567038595207,
          347.45198463508325
        ]
      ],
      "classification_payloads": [
        {
          "class_id": 5,
          "confidence": 1
        }
      ],
      "line_size": 0.5251948400539858,
      "containing_box": {
        "tlx": 113.33643303974293,
        "tly": 345.6890944628269,
        "brx": 116.58125490611403,
        "bry": 349.0275691552452,
        "tlz": 3,
        "brz": 3
      },
      "frame": 25,
      "text_payload": "",
      "annotation_meta": {}
    },
    {
      "id": "0ff0c1e6-4c55-4f9f-895d-411e8c5c4c11",
      "new": true,
      "parent_id": "57a1bb46-d093-4b5d-9b30-69f57de20862",
      "created_by": "helle246",
      "created_at": "2021-06-02T02:13:51.621Z",
      "deprecated": true,
      "spatial_type": "tbar",
      "spatial_payload": [
        [
          117.53429668922627,
          344.45509420157305
        ],
        [
          117.72160234132065,
          344.45509420157305
        ]
      ],
      "classification_payloads": [
        {
          "class_id": 5,
          "confidence": 1
        }
      ],
      "line_size": 0.5251948400539858,
      "containing_box": {
        "tlx": 115.95871216906431,
        "tly": 342.8795096814111,
        "brx": 119.2971868614826,
        "bry": 346.030678721735,
        "tlz": 3,
        "brz": 3
      },
      "frame": 25,
      "text_payload": "",
      "annotation_meta": {}
    },
    {
      "id": "4e12da62-1b50-4404-ab0f-2dfdf9544767",
      "new": true,
      "parent_id": "b42d9ef8-bd31-4646-8bba-013852744d54",
      "created_by": "helle246",
      "created_at": "2021-06-02T02:13:50.308Z",
      "deprecated": true,
      "spatial_type": "tbar",
      "spatial_payload": [
        [
          115.942198646424,
          341.8328150722517
        ],
        [
          116.0358514724712,
          341.6455094201573
        ]
      ],
      "classification_payloads": [
        {
          "class_id": 5,
          "confidence": 1
        }
      ],
      "line_size": 0.5251948400539858,
      "containing_box": {
        "tlx": 114.36661412626205,
        "tly": 340.0699248999953,
        "brx": 117.61143599263315,
        "bry": 343.4083995924137,
        "tlz": 3,
        "brz": 3
      },
      "frame": 25,
      "text_payload": "",
      "annotation_meta": {}
    },
    {
      "id": "3c6a0457-1719-44a0-abad-0e77ea425a27",
      "new": true,
      "parent_id": null,
      "created_by": "helle246",
      "created_at": "2021-06-17T02:14:12.657Z",
      "deprecated": true,
      "spatial_type": "tbar",
      "spatial_payload": [
        [
          113.66576421363524,
          341.87939945852816
        ],
        [
          113.66576421363524,
          341.87939945852816
        ]
      ],
      "classification_payloads": [
        {
          "class_id": 5,
          "confidence": 1
        }
      ],
      "line_size": 0.6721019887859986,
      "containing_box": {
        "tlx": 113.66576421363524,
        "tly": 341.87939945852816,
        "brx": 113.66576421363524,
        "bry": 341.87939945852816,
        "tlz": 3,
        "brz": 3
      },
      "frame": 25,
      "text_payload": "",
      "annotation_meta": {}
    },
    {
      "id": "c97fc84d-ba05-45a8-95e6-72f06ea90447",
      "new": true,
      "parent_id": "f005447c-ce50-497b-902e-03148f8816ef",
      "created_by": "helle246",
      "created_at": "2021-06-02T02:13:49.103Z",
      "deprecated": true,
      "spatial_type": "tbar",
      "spatial_payload": [
        [
          111.82147430034755,
          342.11377355039326
        ],
        [
          111.72782147430034,
          341.9264678982989
        ]
      ],
      "classification_payloads": [
        {
          "class_id": 5,
          "confidence": 1
        }
      ],
      "line_size": 0.5251948400539858,
      "containing_box": {
        "tlx": 110.15223695413839,
        "tly": 340.3508833781369,
        "brx": 113.3970588205095,
        "bry": 343.6893580705552,
        "tlz": 3,
        "brz": 3
      },
      "frame": 25,
      "text_payload": "",
      "annotation_meta": {}
    },
    {
      "id": "469fb73d-d90d-4b34-9785-b529ee0a2545",
      "new": true,
      "parent_id": "6f8f250c-cf24-4614-8914-f5083a062f25",
      "created_by": "helle246",
      "created_at": "2021-06-02T02:13:42.404Z",
      "deprecated": true,
      "spatial_type": "tbar",
      "spatial_payload": [
        [
          107.23248582403512,
          342.488384854582
        ],
        [
          107.23248582403512,
          342.11377355039326
        ]
      ],
      "classification_payloads": [
        {
          "class_id": 5,
          "confidence": 1
        }
      ],
      "line_size": 0.5251948400539858,
      "containing_box": {
        "tlx": 105.65690130387317,
        "tly": 340.5381890302313,
        "brx": 108.80807034419708,
        "bry": 344.063969374744,
        "tlz": 3,
        "brz": 3
      },
      "frame": 25,
      "text_payload": "",
      "annotation_meta": {}
    },
    {
      "id": "11578919-c44f-4f56-96ba-65c09b009919",
      "new": true,
      "parent_id": "5064c8a8-4609-4a6e-be38-ec9020b874d3",
      "created_by": "helle246",
      "created_at": "2021-06-02T02:14:19.468Z",
      "deprecated": true,
      "spatial_type": "tbar",
      "spatial_payload": [
        [
          108.26266691055423,
          348.57581854764953
        ],
        [
          108.26266691055423,
          348.7631241997439
        ]
      ],
      "classification_payloads": [
        {
          "class_id": 5,
          "confidence": 1
        }
      ],
      "line_size": 0.5251948400539858,
      "containing_box": {
        "tlx": 106.68708239039228,
        "tly": 347.0002340274876,
        "brx": 109.83825143071618,
        "bry": 350.33870871990587,
        "tlz": 2,
        "brz": 2
      },
      "frame": 24,
      "text_payload": "",
      "annotation_meta": {}
    },
    {
      "id": "9cc1ab2d-2e61-4b51-a9c0-382853885407",
      "new": true,
      "parent_id": "fcc79fa3-b064-4c8d-96a5-881b401e07b6",
      "created_by": "helle246",
      "created_at": "2021-06-02T02:13:58.453Z",
      "deprecated": true,
      "spatial_type": "tbar",
      "spatial_payload": [
        [
          102.26888604353393,
          347.63929028717763
        ],
        [
          102.08158039143954,
          347.9202487653192
        ]
      ],
      "classification_payloads": [
        {
          "class_id": 5,
          "confidence": 1
        }
      ],
      "line_size": 0.5251948400539858,
      "containing_box": {
        "tlx": 100.50599587127759,
        "tly": 346.0637057670157,
        "brx": 103.84447056369588,
        "bry": 349.4958332854811,
        "tlz": 2,
        "brz": 2
      },
      "frame": 24,
      "text_payload": "",
      "annotation_meta": {}
    },
    {
      "id": "6f9042aa-c364-4b94-9ae5-3bb45d3e35fa",
      "new": true,
      "parent_id": "26eea161-fff6-4a73-b5cf-706987dae84b",
      "created_by": "helle246",
      "created_at": "2021-06-02T02:13:59.489Z",
      "deprecated": true,
      "spatial_type": "tbar",
      "spatial_payload": [
        [
          103.8609840863362,
          345.2979696359978
        ],
        [
          103.76733126028901,
          345.1106639839034
        ]
      ],
      "classification_payloads": [
        {
          "class_id": 5,
          "confidence": 1
        }
      ],
      "line_size": 0.5251948400539858,
      "containing_box": {
        "tlx": 102.19174674012706,
        "tly": 343.53507946374145,
        "brx": 105.43656860649816,
        "bry": 346.87355415615974,
        "tlz": 2,
        "brz": 2
      },
      "frame": 24,
      "text_payload": "",
      "annotation_meta": {}
    },
    {
      "id": "41e5a355-7924-4579-9a19-2698808809bc",
      "new": true,
      "parent_id": "c36d7dd0-ba23-4eb8-9191-f732c784ad1e",
      "created_by": "helle246",
      "created_at": "2021-06-02T02:14:09.899Z",
      "deprecated": true,
      "spatial_type": "tbar",
      "spatial_payload": [
        [
          118.65813060179258,
          342.39473202853486
        ],
        [
          118.93908907993415,
          342.39473202853486
        ]
      ],
      "classification_payloads": [
        {
          "class_id": 5,
          "confidence": 1
        }
      ],
      "line_size": 0.5251948400539858,
      "containing_box": {
        "tlx": 117.08254608163062,
        "tly": 340.8191475083729,
        "brx": 120.5146736000961,
        "bry": 343.9703165486968,
        "tlz": 2,
        "brz": 2
      },
      "frame": 24,
      "text_payload": "",
      "annotation_meta": {}
    },
    {
      "id": "7015088f-1bdc-428a-b413-e76536188105",
      "new": true,
      "parent_id": null,
      "created_by": "helle246",
      "created_at": "2021-06-17T02:14:24.593Z",
      "deprecated": true,
      "spatial_type": "tbar",
      "spatial_payload": [
        [
          115.47198293543359,
          350.95249815407334
        ],
        [
          115.47198293543359,
          351.6245795389285
        ]
      ],
      "classification_payloads": [
        {
          "class_id": 5,
          "confidence": 1
        }
      ],
      "line_size": 0.3448945918245384,
      "containing_box": {
        "tlx": 114.43729915995998,
        "tly": 349.9178143785997,
        "brx": 116.5066667109072,
        "bry": 352.65926331440215,
        "tlz": 1,
        "brz": 1
      },
      "frame": 23,
      "text_payload": "",
      "annotation_meta": {}
    },
    {
      "id": "f3ef3ade-082b-4c00-be64-664d0204385a",
      "new": true,
      "parent_id": null,
      "created_by": "helle246",
      "created_at": "2021-06-17T02:14:25.344Z",
      "deprecated": false,
      "spatial_type": "tbar",
      "spatial_payload": [
        [
          113.32977245554329,
          346.12183078470343
        ],
        [
          113.11974702277605,
          346.2898511309172
        ]
      ],
      "classification_payloads": [
        {
          "class_id": 5,
          "confidence": 1
        }
      ],
      "line_size": 0.3448945918245384,
      "containing_box": {
        "tlx": 112.08506324730244,
        "tly": 345.0871470092298,
        "brx": 114.3644562310169,
        "bry": 347.32453490639085,
        "tlz": 1,
        "brz": 1
      },
      "frame": 23,
      "text_payload": "",
      "annotation_meta": {}
    },
    {
      "id": "2d99b7c3-c4d8-4217-a843-9b2235f65b70",
      "new": true,
      "parent_id": null,
      "created_by": "helle246",
      "created_at": "2021-06-17T02:14:26.162Z",
      "deprecated": false,
      "spatial_type": "tbar",
      "spatial_payload": [
        [
          113.5398056147846,
          343.47558502108524
        ],
        [
          113.16175983580355,
          343.1395443286577
        ]
      ],
      "classification_payloads": [
        {
          "class_id": 5,
          "confidence": 1
        }
      ],
      "line_size": 0.3448945918245384,
      "containing_box": {
        "tlx": 112.12707606032994,
        "tly": 342.10486055318404,
        "brx": 114.57448939025821,
        "bry": 344.5102687965589,
        "tlz": 1,
        "brz": 1
      },
      "frame": 23,
      "text_payload": "",
      "annotation_meta": {}
    },
    {
      "id": "81f63e19-194d-4ba4-ab33-9bd04f0cabd9",
      "new": true,
      "parent_id": null,
      "created_by": "helle246",
      "created_at": "2021-06-17T02:14:26.898Z",
      "deprecated": false,
      "spatial_type": "tbar",
      "spatial_payload": [
        [
          116.64812535893019,
          343.09754696857823
        ],
        [
          116.73213553203708,
          342.80351136270406
        ]
      ],
      "classification_payloads": [
        {
          "class_id": 5,
          "confidence": 1
        }
      ],
      "line_size": 0.3448945918245384,
      "containing_box": {
        "tlx": 115.61344158345658,
        "tly": 341.7688275872304,
        "brx": 117.76681930751069,
        "bry": 344.13223074405187,
        "tlz": 1,
        "brz": 1
      },
      "frame": 23,
      "text_payload": "",
      "annotation_meta": {}
    },
    {
      "id": "cf648e3a-2cbb-4b20-bd72-37dcf63e6f6d",
      "new": true,
      "parent_id": null,
      "created_by": "helle246",
      "created_at": "2021-06-17T02:14:27.930Z",
      "deprecated": true,
      "spatial_type": "tbar",
      "spatial_payload": [
        [
          119.50447124456477,
          347.50808105669046
        ],
        [
          119.79850685043893,
          347.50808105669046
        ]
      ],
      "classification_payloads": [
        {
          "class_id": 5,
          "confidence": 1
        }
      ],
      "line_size": 0.3448945918245384,
      "containing_box": {
        "tlx": 118.46978746909116,
        "tly": 346.4733972812168,
        "brx": 120.83319062591254,
        "bry": 348.5427648321641,
        "tlz": 1,
        "brz": 1
      },
      "frame": 23,
      "text_payload": "",
      "annotation_meta": {}
    },
    {
      "id": "77adbe2d-4653-4df0-b603-2ac2e5785d72",
      "new": true,
      "parent_id": null,
      "created_by": "helle246",
      "created_at": "2021-06-17T02:14:33.025Z",
      "deprecated": false,
      "spatial_type": "tbar",
      "spatial_payload": [
        [
          116.14409136294796,
          346.54187006052683
        ],
        [
          116.31211170916177,
          346.835905666401
        ]
      ],
      "classification_payloads": [
        {
          "class_id": 5,
          "confidence": 1
        }
      ],
      "line_size": 0.3448945918245384,
      "containing_box": {
        "tlx": 115.10940758747435,
        "tly": 345.5071862850532,
        "brx": 117.34679548463538,
        "bry": 347.87058944187464,
        "tlz": 1,
        "brz": 1
      },
      "frame": 23,
      "text_payload": "",
      "annotation_meta": {}
    },
    {
      "id": "e7e7d7b3-d597-4184-b8c8-a15fc3177466",
      "new": true,
      "parent_id": null,
      "created_by": "helle246",
      "created_at": "2021-06-17T02:14:33.730Z",
      "deprecated": false,
      "spatial_type": "tbar",
      "spatial_payload": [
        [
          118.20231356140782,
          345.2817728369874
        ],
        [
          118.37033390762163,
          345.2817728369874
        ]
      ],
      "classification_payloads": [
        {
          "class_id": 5,
          "confidence": 1
        }
      ],
      "line_size": 0.3448945918245384,
      "containing_box": {
        "tlx": 117.16762978593421,
        "tly": 344.24708906151375,
        "brx": 119.40501768309524,
        "bry": 346.316456612461,
        "tlz": 1,
        "brz": 1
      },
      "frame": 23,
      "text_payload": "",
      "annotation_meta": {}
    },
    {
      "id": "9fca75eb-d0ba-4824-b7d5-d0ed63e1dde2",
      "new": true,
      "parent_id": null,
      "created_by": "helle246",
      "created_at": "2021-06-17T02:14:36.282Z",
      "deprecated": false,
      "spatial_type": "tbar",
      "spatial_payload": [
        [
          108.33111822134711,
          347.3400607104767
        ],
        [
          108.07908770202641,
          347.6340963163508
        ]
      ],
      "classification_payloads": [
        {
          "class_id": 5,
          "confidence": 1
        }
      ],
      "line_size": 0.3448945918245384,
      "containing_box": {
        "tlx": 107.0444039265528,
        "tly": 346.30537693500304,
        "brx": 109.36580199682072,
        "bry": 348.66878009182443,
        "tlz": 2,
        "brz": 2
      },
      "frame": 24,
      "text_payload": "",
      "annotation_meta": {}
    },
    {
      "id": "fecfc246-4c0d-414a-80a6-e5a9dd65760f",
      "new": true,
      "parent_id": null,
      "created_by": "helle246",
      "created_at": "2021-06-17T02:14:37.386Z",
      "deprecated": false,
      "spatial_type": "tbar",
      "spatial_payload": [
        [
          117.53023217655263,
          343.3495774878989
        ],
        [
          117.86627286898023,
          343.30757240134545
        ]
      ],
      "classification_payloads": [
        {
          "class_id": 5,
          "confidence": 1
        }
      ],
      "line_size": 0.3448945918245384,
      "containing_box": {
        "tlx": 116.49554840107902,
        "tly": 342.2728886258718,
        "brx": 118.90095664445384,
        "bry": 344.38426126337254,
        "tlz": 2,
        "brz": 2
      },
      "frame": 24,
      "text_payload": "",
      "annotation_meta": {}
    },
    {
      "id": "316ad1f0-28fc-4682-bdfa-d7747e80c25f",
      "new": true,
      "parent_id": null,
      "created_by": "helle246",
      "created_at": "2021-06-17T02:14:38.714Z",
      "deprecated": false,
      "spatial_type": "tbar",
      "spatial_payload": [
        [
          110.59943281534933,
          341.879273259452
        ],
        [
          110.09537177670794,
          341.6272427401313
        ]
      ],
      "classification_payloads": [
        {
          "class_id": 5,
          "confidence": 1
        }
      ],
      "line_size": 0.3448945918245384,
      "containing_box": {
        "tlx": 109.06068800123433,
        "tly": 340.59255896465766,
        "brx": 111.63411659082294,
        "bry": 342.91395703492566,
        "tlz": 3,
        "brz": 3
      },
      "frame": 25,
      "text_payload": "",
      "annotation_meta": {}
    },
    {
      "id": "6bb5eb7e-f99b-441e-bcb1-2a36595a1a90",
      "new": true,
      "parent_id": null,
      "created_by": "helle246",
      "created_at": "2021-06-17T02:14:41.080Z",
      "deprecated": false,
      "spatial_type": "tbar",
      "spatial_payload": [
        [
          108.54113721538599,
          345.113671362796
        ],
        [
          108.45712704227908,
          345.15567644934947
        ]
      ],
      "classification_payloads": [
        {
          "class_id": 5,
          "confidence": 1
        }
      ],
      "line_size": 0.3448945918245384,
      "containing_box": {
        "tlx": 107.42244326680547,
        "tly": 344.0789875873224,
        "brx": 109.5758209908596,
        "bry": 346.1903602248231,
        "tlz": 3,
        "brz": 3
      },
      "frame": 25,
      "text_payload": "",
      "annotation_meta": {}
    },
    {
      "id": "77d5bc13-85fb-4ff6-9c89-03b10b075231",
      "new": true,
      "parent_id": null,
      "created_by": "helle246",
      "created_at": "2021-06-17T02:14:41.810Z",
      "deprecated": false,
      "spatial_type": "tbar",
      "spatial_payload": [
        [
          115.34602304883727,
          347.8020896199054
        ],
        [
          115.64005865471142,
          348.2221404854399
        ]
      ],
      "classification_payloads": [
        {
          "class_id": 5,
          "confidence": 1
        }
      ],
      "line_size": 0.3448945918245384,
      "containing_box": {
        "tlx": 114.31133927336366,
        "tly": 346.7674058444318,
        "brx": 116.67474243018503,
        "bry": 349.25682426091356,
        "tlz": 3,
        "brz": 3
      },
      "frame": 25,
      "text_payload": "",
      "annotation_meta": {}
    },
    {
      "id": "c24c18ba-b3d8-41fe-a80c-d2b2cdae5e42",
      "new": true,
      "parent_id": null,
      "created_by": "helle246",
      "created_at": "2021-06-17T02:14:42.497Z",
      "deprecated": false,
      "spatial_type": "tbar",
      "spatial_payload": [
        [
          117.23627512316466,
          344.7357002730641
        ],
        [
          117.48830564248537,
          344.69369518651064
        ]
      ],
      "classification_payloads": [
        {
          "class_id": 5,
          "confidence": 1
        }
      ],
      "line_size": 0.3448945918245384,
      "containing_box": {
        "tlx": 116.20159134769105,
        "tly": 343.659011411037,
        "brx": 118.52298941795898,
        "bry": 345.7703840485377,
        "tlz": 3,
        "brz": 3
      },
      "frame": 25,
      "text_payload": "",
      "annotation_meta": {}
    },
    {
      "id": "bcb829e1-e1b4-4486-9b37-0689c7cb26aa",
      "new": true,
      "parent_id": null,
      "created_by": "helle246",
      "created_at": "2021-06-17T02:14:43.234Z",
      "deprecated": false,
      "spatial_type": "tbar",
      "spatial_payload": [
        [
          114.37989961937954,
          340.8291937422058
        ],
        [
          114.54791996559334,
          340.4931530497782
        ]
      ],
      "classification_payloads": [
        {
          "class_id": 5,
          "confidence": 1
        }
      ],
      "line_size": 0.3448945918245384,
      "containing_box": {
        "tlx": 113.34521584390593,
        "tly": 339.45846927430455,
        "brx": 115.58260374106695,
        "bry": 341.86387751767944,
        "tlz": 3,
        "brz": 3
      },
      "frame": 25,
      "text_payload": "",
      "annotation_meta": {}
    },
    {
      "id": "a880a0af-cff1-4a69-b3cd-6d19c833834b",
      "new": true,
      "parent_id": null,
      "created_by": "helle246",
      "created_at": "2021-06-17T02:15:05.097Z",
      "deprecated": false,
      "spatial_type": "tbar",
      "spatial_payload": [
        [
          109.80129625071785,
          349.0622692591681
        ],
        [
          109.50726064484371,
          349.4823201247026
        ]
      ],
      "classification_payloads": [
        {
          "class_id": 5,
          "confidence": 1
        }
      ],
      "line_size": 0.3448945918245384,
      "containing_box": {
        "tlx": 108.4725768693701,
        "tly": 348.02758548369445,
        "brx": 110.83598002619146,
        "bry": 350.51700390017623,
        "tlz": 3,
        "brz": 3
      },
      "frame": 25,
      "text_payload": "",
      "annotation_meta": {}
    }
  ]
}